Workbook
Name ArmenianHolidays: Holidays!$A$2:$A$92
Name LoanAmount: Inputs!$B$4
Name AnnualRate: Inputs!$B$5
Name FeeRate: Inputs!$B$6
Name StartDate: Inputs!$B$8
Name FirstPayDate: Inputs!$B$9
Name Tenure: Inputs!$B$10
Name DayConvention: Inputs!$B$12
Name ExtraPayMode: Inputs!$B$13
Name MonthlyRate: Inputs!$B$16
Name EMI: Inputs!$B$17

Sheet Holidays
A1: Armenian Public Holidays
A2: 45292
A3: 45293
A4: 45297
A5: 45318
A6: 45319
A7: 45359
A8: 45406
A9: 45413
A10: 45421
A11: 45440
A12: 45478
A13: 45556
... A92: 47848

Sheet Inputs
A1: DC LOAN CALCULATOR — Amortized Schedule
A2: Parameter | B2: Value | C2: Units / Notes
A3: LOAN PARAMETERS
A4: Loan Amount | B4: 1500000 | C4: AMD
A5: Annual Interest Rate | B5: 0.11 | C5: Daily % stored in DB (0.11 = 0.11%/day = 40.15%/yr) — e.g. contract 28 = 0.11
A6: Annual Fee Rate | B6: 0 | C6: Decimal (0.02 = 2%)
A8: Loan Start Date | B8: 46091 | C8: YYYY-MM-DD
A9: First Payment Date | B9: 46122 | C9: YYYY-MM-DD
A10: Tenure (months) | B10: 60 | C10: months
A11: CONFIGURATION
A12: Day Count Convention | B12: Actual | C12: dropdown
A13: Extra Payment Mode | B13: Reduce Tenure | C13: dropdown
A15: DERIVED CALCULATIONS (formulas — do not edit)
A16: Combined Monthly Rate | B16: =B5*365/100/12+B6/100/12 | C16: Source: ContractService.php L466-467 — interestAnnualPercent = rate*365 → monthlyRate = annualPercent/100/12 (rate stored as daily-%, so *365 gives annual-%, /100 gives decimal, /12 gives monthly)
A17: Monthly Payment (EMI) | B17: =-PMT(B16,B10,B4) | C17: Source: ContractService.php L474 — -excelPmt(allMonthlyRate, months, loanAmount)
A18: Total Scheduled Payments | B18: =B17*B10 | C18: Sum of all EMIs
A19: Total Interest + Fee Cost | B19: =B18-B4 | C19: Total cost of credit
A20: Effective Annual Rate (approx) | B20: =(1+B16)^12-1 | C20: Approximate — backend uses XIRR; see EffectiveRateService.php

Sheet Schedule
A1: AMORTIZATION SCHEDULE — DC_New_backend logic
A2: # | B2: Period Start | C2: Due Date (adj.) | D2: Days | E2: Opening Balance | F2: Accrued Interest | G2: Principal Due | H2: Payment Received | I2: Payment Date | J2: Interest Paid | K2: Principal Paid | L2: Unpaid Carried | M2: Closing Balance | N2: Status
A3: =IF(1<=Tenure,1,"") | B3: =IF(1<=Tenure,StartDate,"") | C3: =IF(1<=Tenure,WORKDAY.INTL(EDATE(FirstPayDate,0)-1,1,1,ArmenianHolidays),"") | D3: =IF(1<=Tenure,IF(1=Tenure,C3-StartDate+1,C3-StartDate),"") | E3: =IF(1<=Tenure,LoanAmount,"") | F3: =IF(1<=Tenure,E3*D3*(AnnualRate/100),"") | G3: =IF(1<=Tenure,IF(1=Tenure,E3,EMI-F3),"") | H3: =IF(1<=Tenure,IFERROR(SUMIFS(Payments!$C:$C,Payments!$B:$B,A3),0),"") | I3: =IF(1<=Tenure,IFERROR(AGGREGATE(15,6,Payments!$A$3:$A$200/(Payments!$B$3:$B$200=A3),1),""),"") | J3: =IF(1<=Tenure,IF(H3=0,0,IF(AND(I3<>"",I3<>0,I3<C3),MIN(F3,MAX(0,H3-K3)-IFERROR(MIN(MAX(0,(MAX(0,H3-K3)-F3)/(1-MAX(0,C3-I3)*(AnnualRate/100))),E3,MAX(0,H3-K3)),0)),MIN(F3,MAX(0,H3-K3)))),"") | K3: =IF(1<=Tenure,IF(H3=0,0,MIN(E3,MAX(0,MAX(0,H3-K3)-L3))),"") | L3: =IF(1<=Tenure,MAX(0,F3+G3+J3-K3-L3-M3),"") | M3: =IF(1<=Tenure,IF(1=Tenure,0,MAX(0,E3-M3)),"") | N3: =IF(1>Tenure,"",IF(AND(H3>0,H3>=F3+G3+J3),"Paid",IF(AND(H3>0,H3<F3+G3),"Partial",IF(AND(H3=0,TODAY()>C3),"Overdue","Pending"))))
A4: =IF(2<=Tenure,2,"") | B4: =IF(2<=Tenure,C3,"") | C4: =IF(2<=Tenure,WORKDAY.INTL(EDATE(FirstPayDate,1)-1,1,1,ArmenianHolidays),"") | D4: =IF(2<=Tenure,IF(2=Tenure,C4-C3+1,C4-C3),"") | E4: =IF(2<=Tenure,O3,"") | F4: =IF(2<=Tenure,E4*D4*(AnnualRate/100),"") | G4: =IF(2<=Tenure,IF(2=Tenure,E4,EMI-F4),"") | H4: =IF(2<=Tenure,IFERROR(SUMIFS(Payments!$C:$C,Payments!$B:$B,A4),0),"") | I4: =IF(2<=Tenure,IFERROR(AGGREGATE(15,6,Payments!$A$3:$A$200/(Payments!$B$3:$B$200=A4),1),""),"") | J4: =IF(2<=Tenure,IF(H4=0,0,IF(AND(I4<>"",I4<>0,I4<C4),MIN(F4,MAX(0,H4-K4)-IFERROR(MIN(MAX(0,(MAX(0,H4-K4)-F4)/(1-MAX(0,C4-I4)*(AnnualRate/100))),E4,MAX(0,H4-K4)),0)),MIN(F4,MAX(0,H4-K4)))),"") | K4: =IF(2<=Tenure,IF(H4=0,0,MIN(E4,MAX(0,MAX(0,H4-K4)-L4))),"") | L4: =IF(2<=Tenure,MAX(0,F4+G4+J4-K4-L4-M4),"") | M4: =IF(2<=Tenure,IF(2=Tenure,0,MAX(0,E4-M4)),"") | N4: =IF(2>Tenure,"",IF(AND(H4>0,H4>=F4+G4+J4),"Paid",IF(AND(H4>0,H4<F4+G4),"Partial",IF(AND(H4=0,TODAY()>C4),"Overdue","Pending"))))
A5: =IF(3<=Tenure,3,"") | B5: =IF(3<=Tenure,C4,"") | C5: =IF(3<=Tenure,WORKDAY.INTL(EDATE(FirstPayDate,2)-1,1,1,ArmenianHolidays),"") | D5: =IF(3<=Tenure,IF(3=Tenure,C5-C4+1,C5-C4),"") | E5: =IF(3<=Tenure,O4,"") | F5: =IF(3<=Tenure,E5*D5*(AnnualRate/100),"") | G5: =IF(3<=Tenure,IF(3=Tenure,E5,EMI-F5),"") | H5: =IF(3<=Tenure,IFERROR(SUMIFS(Payments!$C:$C,Payments!$B:$B,A5),0),"") | I5: =IF(3<=Tenure,IFERROR(AGGREGATE(15,6,Payments!$A$3:$A$200/(Payments!$B$3:$B$200=A5),1),""),"") | J5: =IF(3<=Tenure,IF(H5=0,0,IF(AND(I5<>"",I5<>0,I5<C5),MIN(F5,MAX(0,H5-K5)-IFERROR(MIN(MAX(0,(MAX(0,H5-K5)-F5)/(1-MAX(0,C5-I5)*(AnnualRate/100))),E5,MAX(0,H5-K5)),0)),MIN(F5,MAX(0,H5-K5)))),"") | K5: =IF(3<=Tenure,IF(H5=0,0,MIN(E5,MAX(0,MAX(0,H5-K5)-L5))),"") | L5: =IF(3<=Tenure,MAX(0,F5+G5+J5-K5-L5-M5),"") | M5: =IF(3<=Tenure,IF(3=Tenure,0,MAX(0,E5-M5)),"") | N5: =IF(3>Tenure,"",IF(AND(H5>0,H5>=F5+G5+J5),"Paid",IF(AND(H5>0,H5<F5+G5),"Partial",IF(AND(H5=0,TODAY()>C5),"Overdue","Pending"))))
A6: =IF(4<=Tenure,4,"") | B6: =IF(4<=Tenure,C5,"") | C6: =IF(4<=Tenure,WORKDAY.INTL(EDATE(FirstPayDate,3)-1,1,1,ArmenianHolidays),"") | D6: =IF(4<=Tenure,IF(4=Tenure,C6-C5+1,C6-C5),"") | E6: =IF(4<=Tenure,O5,"") | F6: =IF(4<=Tenure,E6*D6*(AnnualRate/100),"") | G6: =IF(4<=Tenure,IF(4=Tenure,E6,EMI-F6),"") | H6: =IF(4<=Tenure,IFERROR(SUMIFS(Payments!$C:$C,Payments!$B:$B,A6),0),"") | I6: =IF(4<=Tenure,IFERROR(AGGREGATE(15,6,Payments!$A$3:$A$200/(Payments!$B$3:$B$200=A6),1),""),"") | J6: =IF(4<=Tenure,IF(H6=0,0,IF(AND(I6<>"",I6<>0,I6<C6),MIN(F6,MAX(0,H6-K6)-IFERROR(MIN(MAX(0,(MAX(0,H6-K6)-F6)/(1-MAX(0,C6-I6)*(AnnualRate/100))),E6,MAX(0,H6-K6)),0)),MIN(F6,MAX(0,H6-K6)))),"") | K6: =IF(4<=Tenure,IF(H6=0,0,MIN(E6,MAX(0,MAX(0,H6-K6)-L6))),"") | L6: =IF(4<=Tenure,MAX(0,F6+G6+J6-K6-L6-M6),"") | M6: =IF(4<=Tenure,IF(4=Tenure,0,MAX(0,E6-M6)),"") | N6: =IF(4>Tenure,"",IF(AND(H6>0,H6>=F6+G6+J6),"Paid",IF(AND(H6>0,H6<F6+G6),"Partial",IF(AND(H6=0,TODAY()>C6),"Overdue","Pending"))))
A7: =IF(5<=Tenure,5,"") | B7: =IF(5<=Tenure,C6,"") | C7: =IF(5<=Tenure,WORKDAY.INTL(EDATE(FirstPayDate,4)-1,1,1,ArmenianHolidays),"") | D7: =IF(5<=Tenure,IF(5=Tenure,C7-C6+1,C7-C6),"") | E7: =IF(5<=Tenure,O6,"") | F7: =IF(5<=Tenure,E7*D7*(AnnualRate/100),"") | G7: =IF(5<=Tenure,IF(5=Tenure,E7,EMI-F7),"") | H7: =IF(5<=Tenure,IFERROR(SUMIFS(Payments!$C:$C,Payments!$B:$B,A7),0),"") | I7: =IF(5<=Tenure,IFERROR(AGGREGATE(15,6,Payments!$A$3:$A$200/(Payments!$B$3:$B$200=A7),1),""),"") | J7: =IF(5<=Tenure,IF(H7=0,0,IF(AND(I7<>"",I7<>0,I7<C7),MIN(F7,MAX(0,H7-K7)-IFERROR(MIN(MAX(0,(MAX(0,H7-K7)-F7)/(1-MAX(0,C7-I7)*(AnnualRate/100))),E7,MAX(0,H7-K7)),0)),MIN(F7,MAX(0,H7-K7)))),"") | K7: =IF(5<=Tenure,IF(H7=0,0,MIN(E7,MAX(0,MAX(0,H7-K7)-L7))),"") | L7: =IF(5<=Tenure,MAX(0,F7+G7+J7-K7-L7-M7),"") | M7: =IF(5<=Tenure,IF(5=Tenure,0,MAX(0,E7-M7)),"") | N7: =IF(5>Tenure,"",IF(AND(H7>0,H7>=F7+G7+J7),"Paid",IF(AND(H7>0,H7<F7+G7),"Partial",IF(AND(H7=0,TODAY()>C7),"Overdue","Pending"))))
A8: =IF(6<=Tenure,6,"") | B8: =IF(6<=Tenure,C7,"") | C8: =IF(6<=Tenure,WORKDAY.INTL(EDATE(FirstPayDate,5)-1,1,1,ArmenianHolidays),"") | D8: =IF(6<=Tenure,IF(6=Tenure,C8-C7+1,C8-C7),"") | E8: =IF(6<=Tenure,O7,"") | F8: =IF(6<=Tenure,E8*D8*(AnnualRate/100),"") | G8: =IF(6<=Tenure,IF(6=Tenure,E8,EMI-F8),"") | H8: =IF(6<=Tenure,IFERROR(SUMIFS(Payments!$C:$C,Payments!$B:$B,A8),0),"") | I8: =IF(6<=Tenure,IFERROR(AGGREGATE(15,6,Payments!$A$3:$A$200/(Payments!$B$3:$B$200=A8),1),""),"") | J8: =IF(6<=Tenure,IF(H8=0,0,IF(AND(I8<>"",I8<>0,I8<C8),MIN(F8,MAX(0,H8-K8)-IFERROR(MIN(MAX(0,(MAX(0,H8-K8)-F8)/(1-MAX(0,C8-I8)*(AnnualRate/100))),E8,MAX(0,H8-K8)),0)),MIN(F8,MAX(0,H8-K8)))),"") | K8: =IF(6<=Tenure,IF(H8=0,0,MIN(E8,MAX(0,MAX(0,H8-K8)-L8))),"") | L8: =IF(6<=Tenure,MAX(0,F8+G8+J8-K8-L8-M8),"") | M8: =IF(6<=Tenure,IF(6=Tenure,0,MAX(0,E8-M8)),"") | N8: =IF(6>Tenure,"",IF(AND(H8>0,H8>=F8+G8+J8),"Paid",IF(AND(H8>0,H8<F8+G8),"Partial",IF(AND(H8=0,TODAY()>C8),"Overdue","Pending"))))
A9: =IF(7<=Tenure,7,"") | B9: =IF(7<=Tenure,C8,"") | C9: =IF(7<=Tenure,WORKDAY.INTL(EDATE(FirstPayDate,6)-1,1,1,ArmenianHolidays),"") | D9: =IF(7<=Tenure,IF(7=Tenure,C9-C8+1,C9-C8),"") | E9: =IF(7<=Tenure,O8,"") | F9: =IF(7<=Tenure,E9*D9*(AnnualRate/100),"") | G9: =IF(7<=Tenure,IF(7=Tenure,E9,EMI-F9),"") | H9: =IF(7<=Tenure,IFERROR(SUMIFS(Payments!$C:$C,Payments!$B:$B,A9),0),"") | I9: =IF(7<=Tenure,IFERROR(AGGREGATE(15,6,Payments!$A$3:$A$200/(Payments!$B$3:$B$200=A9),1),""),"") | J9: =IF(7<=Tenure,IF(H9=0,0,IF(AND(I9<>"",I9<>0,I9<C9),MIN(F9,MAX(0,H9-K9)-IFERROR(MIN(MAX(0,(MAX(0,H9-K9)-F9)/(1-MAX(0,C9-I9)*(AnnualRate/100))),E9,MAX(0,H9-K9)),0)),MIN(F9,MAX(0,H9-K9)))),"") | K9: =IF(7<=Tenure,IF(H9=0,0,MIN(E9,MAX(0,MAX(0,H9-K9)-L9))),"") | L9: =IF(7<=Tenure,MAX(0,F9+G9+J9-K9-L9-M9),"") | M9: =IF(7<=Tenure,IF(7=Tenure,0,MAX(0,E9-M9)),"") | N9: =IF(7>Tenure,"",IF(AND(H9>0,H9>=F9+G9+J9),"Paid",IF(AND(H9>0,H9<F9+G9),"Partial",IF(AND(H9=0,TODAY()>C9),"Overdue","Pending"))))
A10: =IF(8<=Tenure,8,"") | B10: =IF(8<=Tenure,C9,"") | C10: =IF(8<=Tenure,WORKDAY.INTL(EDATE(FirstPayDate,7)-1,1,1,ArmenianHolidays),"") | D10: =IF(8<=Tenure,IF(8=Tenure,C10-C9+1,C10-C9),"") | E10: =IF(8<=Tenure,O9,"") | F10: =IF(8<=Tenure,E10*D10*(AnnualRate/100),"") | G10: =IF(8<=Tenure,IF(8=Tenure,E10,EMI-F10),"") | H10: =IF(8<=Tenure,IFERROR(SUMIFS(Payments!$C:$C,Payments!$B:$B,A10),0),"") | I10: =IF(8<=Tenure,IFERROR(AGGREGATE(15,6,Payments!$A$3:$A$200/(Payments!$B$3:$B$200=A10),1),""),"") | J10: =IF(8<=Tenure,IF(H10=0,0,IF(AND(I10<>"",I10<>0,I10<C10),MIN(F10,MAX(0,H10-K10)-IFERROR(MIN(MAX(0,(MAX(0,H10-K10)-F10)/(1-MAX(0,C10-I10)*(AnnualRate/100))),E10,MAX(0,H10-K10)),0)),MIN(F10,MAX(0,H10-K10)))),"") | K10: =IF(8<=Tenure,IF(H10=0,0,MIN(E10,MAX(0,MAX(0,H10-K10)-L10))),"") | L10: =IF(8<=Tenure,MAX(0,F10+G10+J10-K10-L10-M10),"") | M10: =IF(8<=Tenure,IF(8=Tenure,0,MAX(0,E10-M10)),"") | N10: =IF(8>Tenure,"",IF(AND(H10>0,H10>=F10+G10+J10),"Paid",IF(AND(H10>0,H10<F10+G10),"Partial",IF(AND(H10=0,TODAY()>C10),"Overdue","Pending"))))
A11: =IF(9<=Tenure,9,"") | B11: =IF(9<=Tenure,C10,"") | C11: =IF(9<=Tenure,WORKDAY.INTL(EDATE(FirstPayDate,8)-1,1,1,ArmenianHolidays),"") | D11: =IF(9<=Tenure,IF(9=Tenure,C11-C10+1,C11-C10),"") | E11: =IF(9<=Tenure,O10,"") | F11: =IF(9<=Tenure,E11*D11*(AnnualRate/100),"") | G11: =IF(9<=Tenure,IF(9=Tenure,E11,EMI-F11),"") | H11: =IF(9<=Tenure,IFERROR(SUMIFS(Payments!$C:$C,Payments!$B:$B,A11),0),"") | I11: =IF(9<=Tenure,IFERROR(AGGREGATE(15,6,Payments!$A$3:$A$200/(Payments!$B$3:$B$200=A11),1),""),"") | J11: =IF(9<=Tenure,IF(H11=0,0,IF(AND(I11<>"",I11<>0,I11<C11),MIN(F11,MAX(0,H11-K11)-IFERROR(MIN(MAX(0,(MAX(0,H11-K11)-F11)/(1-MAX(0,C11-I11)*(AnnualRate/100))),E11,MAX(0,H11-K11)),0)),MIN(F11,MAX(0,H11-K11)))),"") | K11: =IF(9<=Tenure,IF(H11=0,0,MIN(E11,MAX(0,MAX(0,H11-K11)-L11))),"") | L11: =IF(9<=Tenure,MAX(0,F11+G11+J11-K11-L11-M11),"") | M11: =IF(9<=Tenure,IF(9=Tenure,0,MAX(0,E11-M11)),"") | N11: =IF(9>Tenure,"",IF(AND(H11>0,H11>=F11+G11+J11),"Paid",IF(AND(H11>0,H11<F11+G11),"Partial",IF(AND(H11=0,TODAY()>C11),"Overdue","Pending"))))
A12: =IF(10<=Tenure,10,"") | B12: =IF(10<=Tenure,C11,"") | C12: =IF(10<=Tenure,WORKDAY.INTL(EDATE(FirstPayDate,9)-1,1,1,ArmenianHolidays),"") | D12: =IF(10<=Tenure,IF(10=Tenure,C12-C11+1,C12-C11),"") | E12: =IF(10<=Tenure,O11,"") | F12: =IF(10<=Tenure,E12*D12*(AnnualRate/100),"") | G12: =IF(10<=Tenure,IF(10=Tenure,E12,EMI-F12),"") | H12: =IF(10<=Tenure,IFERROR(SUMIFS(Payments!$C:$C,Payments!$B:$B,A12),0),"") | I12: =IF(10<=Tenure,IFERROR(AGGREGATE(15,6,Payments!$A$3:$A$200/(Payments!$B$3:$B$200=A12),1),""),"") | J12: =IF(10<=Tenure,IF(H12=0,0,IF(AND(I12<>"",I12<>0,I12<C12),MIN(F12,MAX(0,H12-K12)-IFERROR(MIN(MAX(0,(MAX(0,H12-K12)-F12)/(1-MAX(0,C12-I12)*(AnnualRate/100))),E12,MAX(0,H12-K12)),0)),MIN(F12,MAX(0,H12-K12)))),"") | K12: =IF(10<=Tenure,IF(H12=0,0,MIN(E12,MAX(0,MAX(0,H12-K12)-L12))),"") | L12: =IF(10<=Tenure,MAX(0,F12+G12+J12-K12-L12-M12),"") | M12: =IF(10<=Tenure,IF(10=Tenure,0,MAX(0,E12-M12)),"") | N12: =IF(10>Tenure,"",IF(AND(H12>0,H12>=F12+G12+J12),"Paid",IF(AND(H12>0,H12<F12+G12),"Partial",IF(AND(H12=0,TODAY()>C12),"Overdue","Pending"))))
A13: =IF(11<=Tenure,11,"") | B13: =IF(11<=Tenure,C12,"") | C13: =IF(11<=Tenure,WORKDAY.INTL(EDATE(FirstPayDate,10)-1,1,1,ArmenianHolidays),"") | D13: =IF(11<=Tenure,IF(11=Tenure,C13-C12+1,C13-C12),"") | E13: =IF(11<=Tenure,O12,"") | F13: =IF(11<=Tenure,E13*D13*(AnnualRate/100),"") | G13: =IF(11<=Tenure,IF(11=Tenure,E13,EMI-F13),"") | H13: =IF(11<=Tenure,IFERROR(SUMIFS(Payments!$C:$C,Payments!$B:$B,A13),0),"") | I13: =IF(11<=Tenure,IFERROR(AGGREGATE(15,6,Payments!$A$3:$A$200/(Payments!$B$3:$B$200=A13),1),""),"") | J13: =IF(11<=Tenure,IF(H13=0,0,IF(AND(I13<>"",I13<>0,I13<C13),MIN(F13,MAX(0,H13-K13)-IFERROR(MIN(MAX(0,(MAX(0,H13-K13)-F13)/(1-MAX(0,C13-I13)*(AnnualRate/100))),E13,MAX(0,H13-K13)),0)),MIN(F13,MAX(0,H13-K13)))),"") | K13: =IF(11<=Tenure,IF(H13=0,0,MIN(E13,MAX(0,MAX(0,H13-K13)-L13))),"") | L13: =IF(11<=Tenure,MAX(0,F13+G13+J13-K13-L13-M13),"") | M13: =IF(11<=Tenure,IF(11=Tenure,0,MAX(0,E13-M13)),"") | N13: =IF(11>Tenure,"",IF(AND(H13>0,H13>=F13+G13+J13),"Paid",IF(AND(H13>0,H13<F13+G13),"Partial",IF(AND(H13=0,TODAY()>C13),"Overdue","Pending"))))
A14: =IF(12<=Tenure,12,"") | B14: =IF(12<=Tenure,C13,"") | C14: =IF(12<=Tenure,WORKDAY.INTL(EDATE(FirstPayDate,11)-1,1,1,ArmenianHolidays),"") | D14: =IF(12<=Tenure,IF(12=Tenure,C14-C13+1,C14-C13),"") | E14: =IF(12<=Tenure,O13,"") | F14: =IF(12<=Tenure,E14*D14*(AnnualRate/100),"") | G14: =IF(12<=Tenure,IF(12=Tenure,E14,EMI-F14),"") | H14: =IF(12<=Tenure,IFERROR(SUMIFS(Payments!$C:$C,Payments!$B:$B,A14),0),"") | I14: =IF(12<=Tenure,IFERROR(AGGREGATE(15,6,Payments!$A$3:$A$200/(Payments!$B$3:$B$200=A14),1),""),"") | J14: =IF(12<=Tenure,IF(H14=0,0,IF(AND(I14<>"",I14<>0,I14<C14),MIN(F14,MAX(0,H14-K14)-IFERROR(MIN(MAX(0,(MAX(0,H14-K14)-F14)/(1-MAX(0,C14-I14)*(AnnualRate/100))),E14,MAX(0,H14-K14)),0)),MIN(F14,MAX(0,H14-K14)))),"") | K14: =IF(12<=Tenure,IF(H14=0,0,MIN(E14,MAX(0,MAX(0,H14-K14)-L14))),"") | L14: =IF(12<=Tenure,MAX(0,F14+G14+J14-K14-L14-M14),"") | M14: =IF(12<=Tenure,IF(12=Tenure,0,MAX(0,E14-M14)),"") | N14: =IF(12>Tenure,"",IF(AND(H14>0,H14>=F14+G14+J14),"Paid",IF(AND(H14>0,H14<F14+G14),"Partial",IF(AND(H14=0,TODAY()>C14),"Overdue","Pending"))))
A15: =IF(13<=Tenure,13,"") | B15: =IF(13<=Tenure,C14,"") | C15: =IF(13<=Tenure,WORKDAY.INTL(EDATE(FirstPayDate,12)-1,1,1,ArmenianHolidays),"") | D15: =IF(13<=Tenure,IF(13=Tenure,C15-C14+1,C15-C14),"") | E15: =IF(13<=Tenure,O14,"") | F15: =IF(13<=Tenure,E15*D15*(AnnualRate/100),"") | G15: =IF(13<=Tenure,IF(13=Tenure,E15,EMI-F15),"") | H15: =IF(13<=Tenure,IFERROR(SUMIFS(Payments!$C:$C,Payments!$B:$B,A15),0),"") | I15: =IF(13<=Tenure,IFERROR(AGGREGATE(15,6,Payments!$A$3:$A$200/(Payments!$B$3:$B$200=A15),1),""),"") | J15: =IF(13<=Tenure,IF(H15=0,0,IF(AND(I15<>"",I15<>0,I15<C15),MIN(F15,MAX(0,H15-K15)-IFERROR(MIN(MAX(0,(MAX(0,H15-K15)-F15)/(1-MAX(0,C15-I15)*(AnnualRate/100))),E15,MAX(0,H15-K15)),0)),MIN(F15,MAX(0,H15-K15)))),"") | K15: =IF(13<=Tenure,IF(H15=0,0,MIN(E15,MAX(0,MAX(0,H15-K15)-L15))),"") | L15: =IF(13<=Tenure,MAX(0,F15+G15+J15-K15-L15-M15),"") | M15: =IF(13<=Tenure,IF(13=Tenure,0,MAX(0,E15-M15)),"") | N15: =IF(13>Tenure,"",IF(AND(H15>0,H15>=F15+G15+J15),"Paid",IF(AND(H15>0,H15<F15+G15),"Partial",IF(AND(H15=0,TODAY()>C15),"Overdue","Pending"))))
A16: =IF(14<=Tenure,14,"") | B16: =IF(14<=Tenure,C15,"") | C16: =IF(14<=Tenure,WORKDAY.INTL(EDATE(FirstPayDate,13)-1,1,1,ArmenianHolidays),"") | D16: =IF(14<=Tenure,IF(14=Tenure,C16-C15+1,C16-C15),"") | E16: =IF(14<=Tenure,O15,"") | F16: =IF(14<=Tenure,E16*D16*(AnnualRate/100),"") | G16: =IF(14<=Tenure,IF(14=Tenure,E16,EMI-F16),"") | H16: =IF(14<=Tenure,IFERROR(SUMIFS(Payments!$C:$C,Payments!$B:$B,A16),0),"") | I16: =IF(14<=Tenure,IFERROR(AGGREGATE(15,6,Payments!$A$3:$A$200/(Payments!$B$3:$B$200=A16),1),""),"") | J16: =IF(14<=Tenure,IF(H16=0,0,IF(AND(I16<>"",I16<>0,I16<C16),MIN(F16,MAX(0,H16-K16)-IFERROR(MIN(MAX(0,(MAX(0,H16-K16)-F16)/(1-MAX(0,C16-I16)*(AnnualRate/100))),E16,MAX(0,H16-K16)),0)),MIN(F16,MAX(0,H16-K16)))),"") | K16: =IF(14<=Tenure,IF(H16=0,0,MIN(E16,MAX(0,MAX(0,H16-K16)-L16))),"") | L16: =IF(14<=Tenure,MAX(0,F16+G16+J16-K16-L16-M16),"") | M16: =IF(14<=Tenure,IF(14=Tenure,0,MAX(0,E16-M16)),"") | N16: =IF(14>Tenure,"",IF(AND(H16>0,H16>=F16+G16+J16),"Paid",IF(AND(H16>0,H16<F16+G16),"Partial",IF(AND(H16=0,TODAY()>C16),"Overdue","Pending"))))
A17: =IF(15<=Tenure,15,"") | B17: =IF(15<=Tenure,C16,"") | C17: =IF(15<=Tenure,WORKDAY.INTL(EDATE(FirstPayDate,14)-1,1,1,ArmenianHolidays),"") | D17: =IF(15<=Tenure,IF(15=Tenure,C17-C16+1,C17-C16),"") | E17: =IF(15<=Tenure,O16,"") | F17: =IF(15<=Tenure,E17*D17*(AnnualRate/100),"") | G17: =IF(15<=Tenure,IF(15=Tenure,E17,EMI-F17),"") | H17: =IF(15<=Tenure,IFERROR(SUMIFS(Payments!$C:$C,Payments!$B:$B,A17),0),"") | I17: =IF(15<=Tenure,IFERROR(AGGREGATE(15,6,Payments!$A$3:$A$200/(Payments!$B$3:$B$200=A17),1),""),"") | J17: =IF(15<=Tenure,IF(H17=0,0,IF(AND(I17<>"",I17<>0,I17<C17),MIN(F17,MAX(0,H17-K17)-IFERROR(MIN(MAX(0,(MAX(0,H17-K17)-F17)/(1-MAX(0,C17-I17)*(AnnualRate/100))),E17,MAX(0,H17-K17)),0)),MIN(F17,MAX(0,H17-K17)))),"") | K17: =IF(15<=Tenure,IF(H17=0,0,MIN(E17,MAX(0,MAX(0,H17-K17)-L17))),"") | L17: =IF(15<=Tenure,MAX(0,F17+G17+J17-K17-L17-M17),"") | M17: =IF(15<=Tenure,IF(15=Tenure,0,MAX(0,E17-M17)),"") | N17: =IF(15>Tenure,"",IF(AND(H17>0,H17>=F17+G17+J17),"Paid",IF(AND(H17>0,H17<F17+G17),"Partial",IF(AND(H17=0,TODAY()>C17),"Overdue","Pending"))))
A18: =IF(16<=Tenure,16,"") | B18: =IF(16<=Tenure,C17,"") | C18: =IF(16<=Tenure,WORKDAY.INTL(EDATE(FirstPayDate,15)-1,1,1,ArmenianHolidays),"") | D18: =IF(16<=Tenure,IF(16=Tenure,C18-C17+1,C18-C17),"") | E18: =IF(16<=Tenure,O17,"") | F18: =IF(16<=Tenure,E18*D18*(AnnualRate/100),"") | G18: =IF(16<=Tenure,IF(16=Tenure,E18,EMI-F18),"") | H18: =IF(16<=Tenure,IFERROR(SUMIFS(Payments!$C:$C,Payments!$B:$B,A18),0),"") | I18: =IF(16<=Tenure,IFERROR(AGGREGATE(15,6,Payments!$A$3:$A$200/(Payments!$B$3:$B$200=A18),1),""),"") | J18: =IF(16<=Tenure,IF(H18=0,0,IF(AND(I18<>"",I18<>0,I18<C18),MIN(F18,MAX(0,H18-K18)-IFERROR(MIN(MAX(0,(MAX(0,H18-K18)-F18)/(1-MAX(0,C18-I18)*(AnnualRate/100))),E18,MAX(0,H18-K18)),0)),MIN(F18,MAX(0,H18-K18)))),"") | K18: =IF(16<=Tenure,IF(H18=0,0,MIN(E18,MAX(0,MAX(0,H18-K18)-L18))),"") | L18: =IF(16<=Tenure,MAX(0,F18+G18+J18-K18-L18-M18),"") | M18: =IF(16<=Tenure,IF(16=Tenure,0,MAX(0,E18-M18)),"") | N18: =IF(16>Tenure,"",IF(AND(H18>0,H18>=F18+G18+J18),"Paid",IF(AND(H18>0,H18<F18+G18),"Partial",IF(AND(H18=0,TODAY()>C18),"Overdue","Pending"))))
A19: =IF(17<=Tenure,17,"") | B19: =IF(17<=Tenure,C18,"") | C19: =IF(17<=Tenure,WORKDAY.INTL(EDATE(FirstPayDate,16)-1,1,1,ArmenianHolidays),"") | D19: =IF(17<=Tenure,IF(17=Tenure,C19-C18+1,C19-C18),"") | E19: =IF(17<=Tenure,O18,"") | F19: =IF(17<=Tenure,E19*D19*(AnnualRate/100),"") | G19: =IF(17<=Tenure,IF(17=Tenure,E19,EMI-F19),"") | H19: =IF(17<=Tenure,IFERROR(SUMIFS(Payments!$C:$C,Payments!$B:$B,A19),0),"") | I19: =IF(17<=Tenure,IFERROR(AGGREGATE(15,6,Payments!$A$3:$A$200/(Payments!$B$3:$B$200=A19),1),""),"") | J19: =IF(17<=Tenure,IF(H19=0,0,IF(AND(I19<>"",I19<>0,I19<C19),MIN(F19,MAX(0,H19-K19)-IFERROR(MIN(MAX(0,(MAX(0,H19-K19)-F19)/(1-MAX(0,C19-I19)*(AnnualRate/100))),E19,MAX(0,H19-K19)),0)),MIN(F19,MAX(0,H19-K19)))),"") | K19: =IF(17<=Tenure,IF(H19=0,0,MIN(E19,MAX(0,MAX(0,H19-K19)-L19))),"") | L19: =IF(17<=Tenure,MAX(0,F19+G19+J19-K19-L19-M19),"") | M19: =IF(17<=Tenure,IF(17=Tenure,0,MAX(0,E19-M19)),"") | N19: =IF(17>Tenure,"",IF(AND(H19>0,H19>=F19+G19+J19),"Paid",IF(AND(H19>0,H19<F19+G19),"Partial",IF(AND(H19=0,TODAY()>C19),"Overdue","Pending"))))
A20: =IF(18<=Tenure,18,"") | B20: =IF(18<=Tenure,C19,"") | C20: =IF(18<=Tenure,WORKDAY.INTL(EDATE(FirstPayDate,17)-1,1,1,ArmenianHolidays),"") | D20: =IF(18<=Tenure,IF(18=Tenure,C20-C19+1,C20-C19),"") | E20: =IF(18<=Tenure,O19,"") | F20: =IF(18<=Tenure,E20*D20*(AnnualRate/100),"") | G20: =IF(18<=Tenure,IF(18=Tenure,E20,EMI-F20),"") | H20: =IF(18<=Tenure,IFERROR(SUMIFS(Payments!$C:$C,Payments!$B:$B,A20),0),"") | I20: =IF(18<=Tenure,IFERROR(AGGREGATE(15,6,Payments!$A$3:$A$200/(Payments!$B$3:$B$200=A20),1),""),"") | J20: =IF(18<=Tenure,IF(H20=0,0,IF(AND(I20<>"",I20<>0,I20<C20),MIN(F20,MAX(0,H20-K20)-IFERROR(MIN(MAX(0,(MAX(0,H20-K20)-F20)/(1-MAX(0,C20-I20)*(AnnualRate/100))),E20,MAX(0,H20-K20)),0)),MIN(F20,MAX(0,H20-K20)))),"") | K20: =IF(18<=Tenure,IF(H20=0,0,MIN(E20,MAX(0,MAX(0,H20-K20)-L20))),"") | L20: =IF(18<=Tenure,MAX(0,F20+G20+J20-K20-L20-M20),"") | M20: =IF(18<=Tenure,IF(18=Tenure,0,MAX(0,E20-M20)),"") | N20: =IF(18>Tenure,"",IF(AND(H20>0,H20>=F20+G20+J20),"Paid",IF(AND(H20>0,H20<F20+G20),"Partial",IF(AND(H20=0,TODAY()>C20),"Overdue","Pending"))))
A21: =IF(19<=Tenure,19,"") | B21: =IF(19<=Tenure,C20,"") | C21: =IF(19<=Tenure,WORKDAY.INTL(EDATE(FirstPayDate,18)-1,1,1,ArmenianHolidays),"") | D21: =IF(19<=Tenure,IF(19=Tenure,C21-C20+1,C21-C20),"") | E21: =IF(19<=Tenure,O20,"") | F21: =IF(19<=Tenure,E21*D21*(AnnualRate/100),"") | G21: =IF(19<=Tenure,IF(19=Tenure,E21,EMI-F21),"") | H21: =IF(19<=Tenure,IFERROR(SUMIFS(Payments!$C:$C,Payments!$B:$B,A21),0),"") | I21: =IF(19<=Tenure,IFERROR(AGGREGATE(15,6,Payments!$A$3:$A$200/(Payments!$B$3:$B$200=A21),1),""),"") | J21: =IF(19<=Tenure,IF(H21=0,0,IF(AND(I21<>"",I21<>0,I21<C21),MIN(F21,MAX(0,H21-K21)-IFERROR(MIN(MAX(0,(MAX(0,H21-K21)-F21)/(1-MAX(0,C21-I21)*(AnnualRate/100))),E21,MAX(0,H21-K21)),0)),MIN(F21,MAX(0,H21-K21)))),"") | K21: =IF(19<=Tenure,IF(H21=0,0,MIN(E21,MAX(0,MAX(0,H21-K21)-L21))),"") | L21: =IF(19<=Tenure,MAX(0,F21+G21+J21-K21-L21-M21),"") | M21: =IF(19<=Tenure,IF(19=Tenure,0,MAX(0,E21-M21)),"") | N21: =IF(19>Tenure,"",IF(AND(H21>0,H21>=F21+G21+J21),"Paid",IF(AND(H21>0,H21<F21+G21),"Partial",IF(AND(H21=0,TODAY()>C21),"Overdue","Pending"))))
A22: =IF(20<=Tenure,20,"") | B22: =IF(20<=Tenure,C21,"") | C22: =IF(20<=Tenure,WORKDAY.INTL(EDATE(FirstPayDate,19)-1,1,1,ArmenianHolidays),"") | D22: =IF(20<=Tenure,IF(20=Tenure,C22-C21+1,C22-C21),"") | E22: =IF(20<=Tenure,O21,"") | F22: =IF(20<=Tenure,E22*D22*(AnnualRate/100),"") | G22: =IF(20<=Tenure,IF(20=Tenure,E22,EMI-F22),"") | H22: =IF(20<=Tenure,IFERROR(SUMIFS(Payments!$C:$C,Payments!$B:$B,A22),0),"") | I22: =IF(20<=Tenure,IFERROR(AGGREGATE(15,6,Payments!$A$3:$A$200/(Payments!$B$3:$B$200=A22),1),""),"") | J22: =IF(20<=Tenure,IF(H22=0,0,IF(AND(I22<>"",I22<>0,I22<C22),MIN(F22,MAX(0,H22-K22)-IFERROR(MIN(MAX(0,(MAX(0,H22-K22)-F22)/(1-MAX(0,C22-I22)*(AnnualRate/100))),E22,MAX(0,H22-K22)),0)),MIN(F22,MAX(0,H22-K22)))),"") | K22: =IF(20<=Tenure,IF(H22=0,0,MIN(E22,MAX(0,MAX(0,H22-K22)-L22))),"") | L22: =IF(20<=Tenure,MAX(0,F22+G22+J22-K22-L22-M22),"") | M22: =IF(20<=Tenure,IF(20=Tenure,0,MAX(0,E22-M22)),"") | N22: =IF(20>Tenure,"",IF(AND(H22>0,H22>=F22+G22+J22),"Paid",IF(AND(H22>0,H22<F22+G22),"Partial",IF(AND(H22=0,TODAY()>C22),"Overdue","Pending"))))
A23: =IF(21<=Tenure,21,"") | B23: =IF(21<=Tenure,C22,"") | C23: =IF(21<=Tenure,WORKDAY.INTL(EDATE(FirstPayDate,20)-1,1,1,ArmenianHolidays),"") | D23: =IF(21<=Tenure,IF(21=Tenure,C23-C22+1,C23-C22),"") | E23: =IF(21<=Tenure,O22,"") | F23: =IF(21<=Tenure,E23*D23*(AnnualRate/100),"") | G23: =IF(21<=Tenure,IF(21=Tenure,E23,EMI-F23),"") | H23: =IF(21<=Tenure,IFERROR(SUMIFS(Payments!$C:$C,Payments!$B:$B,A23),0),"") | I23: =IF(21<=Tenure,IFERROR(AGGREGATE(15,6,Payments!$A$3:$A$200/(Payments!$B$3:$B$200=A23),1),""),"") | J23: =IF(21<=Tenure,IF(H23=0,0,IF(AND(I23<>"",I23<>0,I23<C23),MIN(F23,MAX(0,H23-K23)-IFERROR(MIN(MAX(0,(MAX(0,H23-K23)-F23)/(1-MAX(0,C23-I23)*(AnnualRate/100))),E23,MAX(0,H23-K23)),0)),MIN(F23,MAX(0,H23-K23)))),"") | K23: =IF(21<=Tenure,IF(H23=0,0,MIN(E23,MAX(0,MAX(0,H23-K23)-L23))),"") | L23: =IF(21<=Tenure,MAX(0,F23+G23+J23-K23-L23-M23),"") | M23: =IF(21<=Tenure,IF(21=Tenure,0,MAX(0,E23-M23)),"") | N23: =IF(21>Tenure,"",IF(AND(H23>0,H23>=F23+G23+J23),"Paid",IF(AND(H23>0,H23<F23+G23),"Partial",IF(AND(H23=0,TODAY()>C23),"Overdue","Pending"))))
A24: =IF(22<=Tenure,22,"") | B24: =IF(22<=Tenure,C23,"") | C24: =IF(22<=Tenure,WORKDAY.INTL(EDATE(FirstPayDate,21)-1,1,1,ArmenianHolidays),"") | D24: =IF(22<=Tenure,IF(22=Tenure,C24-C23+1,C24-C23),"") | E24: =IF(22<=Tenure,O23,"") | F24: =IF(22<=Tenure,E24*D24*(AnnualRate/100),"") | G24: =IF(22<=Tenure,IF(22=Tenure,E24,EMI-F24),"") | H24: =IF(22<=Tenure,IFERROR(SUMIFS(Payments!$C:$C,Payments!$B:$B,A24),0),"") | I24: =IF(22<=Tenure,IFERROR(AGGREGATE(15,6,Payments!$A$3:$A$200/(Payments!$B$3:$B$200=A24),1),""),"") | J24: =IF(22<=Tenure,IF(H24=0,0,IF(AND(I24<>"",I24<>0,I24<C24),MIN(F24,MAX(0,H24-K24)-IFERROR(MIN(MAX(0,(MAX(0,H24-K24)-F24)/(1-MAX(0,C24-I24)*(AnnualRate/100))),E24,MAX(0,H24-K24)),0)),MIN(F24,MAX(0,H24-K24)))),"") | K24: =IF(22<=Tenure,IF(H24=0,0,MIN(E24,MAX(0,MAX(0,H24-K24)-L24))),"") | L24: =IF(22<=Tenure,MAX(0,F24+G24+J24-K24-L24-M24),"") | M24: =IF(22<=Tenure,IF(22=Tenure,0,MAX(0,E24-M24)),"") | N24: =IF(22>Tenure,"",IF(AND(H24>0,H24>=F24+G24+J24),"Paid",IF(AND(H24>0,H24<F24+G24),"Partial",IF(AND(H24=0,TODAY()>C24),"Overdue","Pending"))))
A25: =IF(23<=Tenure,23,"") | B25: =IF(23<=Tenure,C24,"") | C25: =IF(23<=Tenure,WORKDAY.INTL(EDATE(FirstPayDate,22)-1,1,1,ArmenianHolidays),"") | D25: =IF(23<=Tenure,IF(23=Tenure,C25-C24+1,C25-C24),"") | E25: =IF(23<=Tenure,O24,"") | F25: =IF(23<=Tenure,E25*D25*(AnnualRate/100),"") | G25: =IF(23<=Tenure,IF(23=Tenure,E25,EMI-F25),"") | H25: =IF(23<=Tenure,IFERROR(SUMIFS(Payments!$C:$C,Payments!$B:$B,A25),0),"") | I25: =IF(23<=Tenure,IFERROR(AGGREGATE(15,6,Payments!$A$3:$A$200/(Payments!$B$3:$B$200=A25),1),""),"") | J25: =IF(23<=Tenure,IF(H25=0,0,IF(AND(I25<>"",I25<>0,I25<C25),MIN(F25,MAX(0,H25-K25)-IFERROR(MIN(MAX(0,(MAX(0,H25-K25)-F25)/(1-MAX(0,C25-I25)*(AnnualRate/100))),E25,MAX(0,H25-K25)),0)),MIN(F25,MAX(0,H25-K25)))),"") | K25: =IF(23<=Tenure,IF(H25=0,0,MIN(E25,MAX(0,MAX(0,H25-K25)-L25))),"") | L25: =IF(23<=Tenure,MAX(0,F25+G25+J25-K25-L25-M25),"") | M25: =IF(23<=Tenure,IF(23=Tenure,0,MAX(0,E25-M25)),"") | N25: =IF(23>Tenure,"",IF(AND(H25>0,H25>=F25+G25+J25),"Paid",IF(AND(H25>0,H25<F25+G25),"Partial",IF(AND(H25=0,TODAY()>C25),"Overdue","Pending"))))
A26: =IF(24<=Tenure,24,"") | B26: =IF(24<=Tenure,C25,"") | C26: =IF(24<=Tenure,WORKDAY.INTL(EDATE(FirstPayDate,23)-1,1,1,ArmenianHolidays),"") | D26: =IF(24<=Tenure,IF(24=Tenure,C26-C25+1,C26-C25),"") | E26: =IF(24<=Tenure,O25,"") | F26: =IF(24<=Tenure,E26*D26*(AnnualRate/100),"") | G26: =IF(24<=Tenure,IF(24=Tenure,E26,EMI-F26),"") | H26: =IF(24<=Tenure,IFERROR(SUMIFS(Payments!$C:$C,Payments!$B:$B,A26),0),"") | I26: =IF(24<=Tenure,IFERROR(AGGREGATE(15,6,Payments!$A$3:$A$200/(Payments!$B$3:$B$200=A26),1),""),"") | J26: =IF(24<=Tenure,IF(H26=0,0,IF(AND(I26<>"",I26<>0,I26<C26),MIN(F26,MAX(0,H26-K26)-IFERROR(MIN(MAX(0,(MAX(0,H26-K26)-F26)/(1-MAX(0,C26-I26)*(AnnualRate/100))),E26,MAX(0,H26-K26)),0)),MIN(F26,MAX(0,H26-K26)))),"") | K26: =IF(24<=Tenure,IF(H26=0,0,MIN(E26,MAX(0,MAX(0,H26-K26)-L26))),"") | L26: =IF(24<=Tenure,MAX(0,F26+G26+J26-K26-L26-M26),"") | M26: =IF(24<=Tenure,IF(24=Tenure,0,MAX(0,E26-M26)),"") | N26: =IF(24>Tenure,"",IF(AND(H26>0,H26>=F26+G26+J26),"Paid",IF(AND(H26>0,H26<F26+G26),"Partial",IF(AND(H26=0,TODAY()>C26),"Overdue","Pending"))))
A27: =IF(25<=Tenure,25,"") | B27: =IF(25<=Tenure,C26,"") | C27: =IF(25<=Tenure,WORKDAY.INTL(EDATE(FirstPayDate,24)-1,1,1,ArmenianHolidays),"") | D27: =IF(25<=Tenure,IF(25=Tenure,C27-C26+1,C27-C26),"") | E27: =IF(25<=Tenure,O26,"") | F27: =IF(25<=Tenure,E27*D27*(AnnualRate/100),"") | G27: =IF(25<=Tenure,IF(25=Tenure,E27,EMI-F27),"") | H27: =IF(25<=Tenure,IFERROR(SUMIFS(Payments!$C:$C,Payments!$B:$B,A27),0),"") | I27: =IF(25<=Tenure,IFERROR(AGGREGATE(15,6,Payments!$A$3:$A$200/(Payments!$B$3:$B$200=A27),1),""),"") | J27: =IF(25<=Tenure,IF(H27=0,0,IF(AND(I27<>"",I27<>0,I27<C27),MIN(F27,MAX(0,H27-K27)-IFERROR(MIN(MAX(0,(MAX(0,H27-K27)-F27)/(1-MAX(0,C27-I27)*(AnnualRate/100))),E27,MAX(0,H27-K27)),0)),MIN(F27,MAX(0,H27-K27)))),"") | K27: =IF(25<=Tenure,IF(H27=0,0,MIN(E27,MAX(0,MAX(0,H27-K27)-L27))),"") | L27: =IF(25<=Tenure,MAX(0,F27+G27+J27-K27-L27-M27),"") | M27: =IF(25<=Tenure,IF(25=Tenure,0,MAX(0,E27-M27)),"") | N27: =IF(25>Tenure,"",IF(AND(H27>0,H27>=F27+G27+J27),"Paid",IF(AND(H27>0,H27<F27+G27),"Partial",IF(AND(H27=0,TODAY()>C27),"Overdue","Pending"))))
A28: =IF(26<=Tenure,26,"") | B28: =IF(26<=Tenure,C27,"") | C28: =IF(26<=Tenure,WORKDAY.INTL(EDATE(FirstPayDate,25)-1,1,1,ArmenianHolidays),"") | D28: =IF(26<=Tenure,IF(26=Tenure,C28-C27+1,C28-C27),"") | E28: =IF(26<=Tenure,O27,"") | F28: =IF(26<=Tenure,E28*D28*(AnnualRate/100),"") | G28: =IF(26<=Tenure,IF(26=Tenure,E28,EMI-F28),"") | H28: =IF(26<=Tenure,IFERROR(SUMIFS(Payments!$C:$C,Payments!$B:$B,A28),0),"") | I28: =IF(26<=Tenure,IFERROR(AGGREGATE(15,6,Payments!$A$3:$A$200/(Payments!$B$3:$B$200=A28),1),""),"") | J28: =IF(26<=Tenure,IF(H28=0,0,IF(AND(I28<>"",I28<>0,I28<C28),MIN(F28,MAX(0,H28-K28)-IFERROR(MIN(MAX(0,(MAX(0,H28-K28)-F28)/(1-MAX(0,C28-I28)*(AnnualRate/100))),E28,MAX(0,H28-K28)),0)),MIN(F28,MAX(0,H28-K28)))),"") | K28: =IF(26<=Tenure,IF(H28=0,0,MIN(E28,MAX(0,MAX(0,H28-K28)-L28))),"") | L28: =IF(26<=Tenure,MAX(0,F28+G28+J28-K28-L28-M28),"") | M28: =IF(26<=Tenure,IF(26=Tenure,0,MAX(0,E28-M28)),"") | N28: =IF(26>Tenure,"",IF(AND(H28>0,H28>=F28+G28+J28),"Paid",IF(AND(H28>0,H28<F28+G28),"Partial",IF(AND(H28=0,TODAY()>C28),"Overdue","Pending"))))
A29: =IF(27<=Tenure,27,"") | B29: =IF(27<=Tenure,C28,"") | C29: =IF(27<=Tenure,WORKDAY.INTL(EDATE(FirstPayDate,26)-1,1,1,ArmenianHolidays),"") | D29: =IF(27<=Tenure,IF(27=Tenure,C29-C28+1,C29-C28),"") | E29: =IF(27<=Tenure,O28,"") | F29: =IF(27<=Tenure,E29*D29*(AnnualRate/100),"") | G29: =IF(27<=Tenure,IF(27=Tenure,E29,EMI-F29),"") | H29: =IF(27<=Tenure,IFERROR(SUMIFS(Payments!$C:$C,Payments!$B:$B,A29),0),"") | I29: =IF(27<=Tenure,IFERROR(AGGREGATE(15,6,Payments!$A$3:$A$200/(Payments!$B$3:$B$200=A29),1),""),"") | J29: =IF(27<=Tenure,IF(H29=0,0,IF(AND(I29<>"",I29<>0,I29<C29),MIN(F29,MAX(0,H29-K29)-IFERROR(MIN(MAX(0,(MAX(0,H29-K29)-F29)/(1-MAX(0,C29-I29)*(AnnualRate/100))),E29,MAX(0,H29-K29)),0)),MIN(F29,MAX(0,H29-K29)))),"") | K29: =IF(27<=Tenure,IF(H29=0,0,MIN(E29,MAX(0,MAX(0,H29-K29)-L29))),"") | L29: =IF(27<=Tenure,MAX(0,F29+G29+J29-K29-L29-M29),"") | M29: =IF(27<=Tenure,IF(27=Tenure,0,MAX(0,E29-M29)),"") | N29: =IF(27>Tenure,"",IF(AND(H29>0,H29>=F29+G29+J29),"Paid",IF(AND(H29>0,H29<F29+G29),"Partial",IF(AND(H29=0,TODAY()>C29),"Overdue","Pending"))))
A30: =IF(28<=Tenure,28,"") | B30: =IF(28<=Tenure,C29,"") | C30: =IF(28<=Tenure,WORKDAY.INTL(EDATE(FirstPayDate,27)-1,1,1,ArmenianHolidays),"") | D30: =IF(28<=Tenure,IF(28=Tenure,C30-C29+1,C30-C29),"") | E30: =IF(28<=Tenure,O29,"") | F30: =IF(28<=Tenure,E30*D30*(AnnualRate/100),"") | G30: =IF(28<=Tenure,IF(28=Tenure,E30,EMI-F30),"") | H30: =IF(28<=Tenure,IFERROR(SUMIFS(Payments!$C:$C,Payments!$B:$B,A30),0),"") | I30: =IF(28<=Tenure,IFERROR(AGGREGATE(15,6,Payments!$A$3:$A$200/(Payments!$B$3:$B$200=A30),1),""),"") | J30: =IF(28<=Tenure,IF(H30=0,0,IF(AND(I30<>"",I30<>0,I30<C30),MIN(F30,MAX(0,H30-K30)-IFERROR(MIN(MAX(0,(MAX(0,H30-K30)-F30)/(1-MAX(0,C30-I30)*(AnnualRate/100))),E30,MAX(0,H30-K30)),0)),MIN(F30,MAX(0,H30-K30)))),"") | K30: =IF(28<=Tenure,IF(H30=0,0,MIN(E30,MAX(0,MAX(0,H30-K30)-L30))),"") | L30: =IF(28<=Tenure,MAX(0,F30+G30+J30-K30-L30-M30),"") | M30: =IF(28<=Tenure,IF(28=Tenure,0,MAX(0,E30-M30)),"") | N30: =IF(28>Tenure,"",IF(AND(H30>0,H30>=F30+G30+J30),"Paid",IF(AND(H30>0,H30<F30+G30),"Partial",IF(AND(H30=0,TODAY()>C30),"Overdue","Pending"))))
A31: =IF(29<=Tenure,29,"") | B31: =IF(29<=Tenure,C30,"") | C31: =IF(29<=Tenure,WORKDAY.INTL(EDATE(FirstPayDate,28)-1,1,1,ArmenianHolidays),"") | D31: =IF(29<=Tenure,IF(29=Tenure,C31-C30+1,C31-C30),"") | E31: =IF(29<=Tenure,O30,"") | F31: =IF(29<=Tenure,E31*D31*(AnnualRate/100),"") | G31: =IF(29<=Tenure,IF(29=Tenure,E31,EMI-F31),"") | H31: =IF(29<=Tenure,IFERROR(SUMIFS(Payments!$C:$C,Payments!$B:$B,A31),0),"") | I31: =IF(29<=Tenure,IFERROR(AGGREGATE(15,6,Payments!$A$3:$A$200/(Payments!$B$3:$B$200=A31),1),""),"") | J31: =IF(29<=Tenure,IF(H31=0,0,IF(AND(I31<>"",I31<>0,I31<C31),MIN(F31,MAX(0,H31-K31)-IFERROR(MIN(MAX(0,(MAX(0,H31-K31)-F31)/(1-MAX(0,C31-I31)*(AnnualRate/100))),E31,MAX(0,H31-K31)),0)),MIN(F31,MAX(0,H31-K31)))),"") | K31: =IF(29<=Tenure,IF(H31=0,0,MIN(E31,MAX(0,MAX(0,H31-K31)-L31))),"") | L31: =IF(29<=Tenure,MAX(0,F31+G31+J31-K31-L31-M31),"") | M31: =IF(29<=Tenure,IF(29=Tenure,0,MAX(0,E31-M31)),"") | N31: =IF(29>Tenure,"",IF(AND(H31>0,H31>=F31+G31+J31),"Paid",IF(AND(H31>0,H31<F31+G31),"Partial",IF(AND(H31=0,TODAY()>C31),"Overdue","Pending"))))
A32: =IF(30<=Tenure,30,"") | B32: =IF(30<=Tenure,C31,"") | C32: =IF(30<=Tenure,WORKDAY.INTL(EDATE(FirstPayDate,29)-1,1,1,ArmenianHolidays),"") | D32: =IF(30<=Tenure,IF(30=Tenure,C32-C31+1,C32-C31),"") | E32: =IF(30<=Tenure,O31,"") | F32: =IF(30<=Tenure,E32*D32*(AnnualRate/100),"") | G32: =IF(30<=Tenure,IF(30=Tenure,E32,EMI-F32),"") | H32: =IF(30<=Tenure,IFERROR(SUMIFS(Payments!$C:$C,Payments!$B:$B,A32),0),"") | I32: =IF(30<=Tenure,IFERROR(AGGREGATE(15,6,Payments!$A$3:$A$200/(Payments!$B$3:$B$200=A32),1),""),"") | J32: =IF(30<=Tenure,IF(H32=0,0,IF(AND(I32<>"",I32<>0,I32<C32),MIN(F32,MAX(0,H32-K32)-IFERROR(MIN(MAX(0,(MAX(0,H32-K32)-F32)/(1-MAX(0,C32-I32)*(AnnualRate/100))),E32,MAX(0,H32-K32)),0)),MIN(F32,MAX(0,H32-K32)))),"") | K32: =IF(30<=Tenure,IF(H32=0,0,MIN(E32,MAX(0,MAX(0,H32-K32)-L32))),"") | L32: =IF(30<=Tenure,MAX(0,F32+G32+J32-K32-L32-M32),"") | M32: =IF(30<=Tenure,IF(30=Tenure,0,MAX(0,E32-M32)),"") | N32: =IF(30>Tenure,"",IF(AND(H32>0,H32>=F32+G32+J32),"Paid",IF(AND(H32>0,H32<F32+G32),"Partial",IF(AND(H32=0,TODAY()>C32),"Overdue","Pending"))))
A33: =IF(31<=Tenure,31,"") | B33: =IF(31<=Tenure,C32,"") | C33: =IF(31<=Tenure,WORKDAY.INTL(EDATE(FirstPayDate,30)-1,1,1,ArmenianHolidays),"") | D33: =IF(31<=Tenure,IF(31=Tenure,C33-C32+1,C33-C32),"") | E33: =IF(31<=Tenure,O32,"") | F33: =IF(31<=Tenure,E33*D33*(AnnualRate/100),"") | G33: =IF(31<=Tenure,IF(31=Tenure,E33,EMI-F33),"") | H33: =IF(31<=Tenure,IFERROR(SUMIFS(Payments!$C:$C,Payments!$B:$B,A33),0),"") | I33: =IF(31<=Tenure,IFERROR(AGGREGATE(15,6,Payments!$A$3:$A$200/(Payments!$B$3:$B$200=A33),1),""),"") | J33: =IF(31<=Tenure,IF(H33=0,0,IF(AND(I33<>"",I33<>0,I33<C33),MIN(F33,MAX(0,H33-K33)-IFERROR(MIN(MAX(0,(MAX(0,H33-K33)-F33)/(1-MAX(0,C33-I33)*(AnnualRate/100))),E33,MAX(0,H33-K33)),0)),MIN(F33,MAX(0,H33-K33)))),"") | K33: =IF(31<=Tenure,IF(H33=0,0,MIN(E33,MAX(0,MAX(0,H33-K33)-L33))),"") | L33: =IF(31<=Tenure,MAX(0,F33+G33+J33-K33-L33-M33),"") | M33: =IF(31<=Tenure,IF(31=Tenure,0,MAX(0,E33-M33)),"") | N33: =IF(31>Tenure,"",IF(AND(H33>0,H33>=F33+G33+J33),"Paid",IF(AND(H33>0,H33<F33+G33),"Partial",IF(AND(H33=0,TODAY()>C33),"Overdue","Pending"))))
A34: =IF(32<=Tenure,32,"") | B34: =IF(32<=Tenure,C33,"") | C34: =IF(32<=Tenure,WORKDAY.INTL(EDATE(FirstPayDate,31)-1,1,1,ArmenianHolidays),"") | D34: =IF(32<=Tenure,IF(32=Tenure,C34-C33+1,C34-C33),"") | E34: =IF(32<=Tenure,O33,"") | F34: =IF(32<=Tenure,E34*D34*(AnnualRate/100),"") | G34: =IF(32<=Tenure,IF(32=Tenure,E34,EMI-F34),"") | H34: =IF(32<=Tenure,IFERROR(SUMIFS(Payments!$C:$C,Payments!$B:$B,A34),0),"") | I34: =IF(32<=Tenure,IFERROR(AGGREGATE(15,6,Payments!$A$3:$A$200/(Payments!$B$3:$B$200=A34),1),""),"") | J34: =IF(32<=Tenure,IF(H34=0,0,IF(AND(I34<>"",I34<>0,I34<C34),MIN(F34,MAX(0,H34-K34)-IFERROR(MIN(MAX(0,(MAX(0,H34-K34)-F34)/(1-MAX(0,C34-I34)*(AnnualRate/100))),E34,MAX(0,H34-K34)),0)),MIN(F34,MAX(0,H34-K34)))),"") | K34: =IF(32<=Tenure,IF(H34=0,0,MIN(E34,MAX(0,MAX(0,H34-K34)-L34))),"") | L34: =IF(32<=Tenure,MAX(0,F34+G34+J34-K34-L34-M34),"") | M34: =IF(32<=Tenure,IF(32=Tenure,0,MAX(0,E34-M34)),"") | N34: =IF(32>Tenure,"",IF(AND(H34>0,H34>=F34+G34+J34),"Paid",IF(AND(H34>0,H34<F34+G34),"Partial",IF(AND(H34=0,TODAY()>C34),"Overdue","Pending"))))
A35: =IF(33<=Tenure,33,"") | B35: =IF(33<=Tenure,C34,"") | C35: =IF(33<=Tenure,WORKDAY.INTL(EDATE(FirstPayDate,32)-1,1,1,ArmenianHolidays),"") | D35: =IF(33<=Tenure,IF(33=Tenure,C35-C34+1,C35-C34),"") | E35: =IF(33<=Tenure,O34,"") | F35: =IF(33<=Tenure,E35*D35*(AnnualRate/100),"") | G35: =IF(33<=Tenure,IF(33=Tenure,E35,EMI-F35),"") | H35: =IF(33<=Tenure,IFERROR(SUMIFS(Payments!$C:$C,Payments!$B:$B,A35),0),"") | I35: =IF(33<=Tenure,IFERROR(AGGREGATE(15,6,Payments!$A$3:$A$200/(Payments!$B$3:$B$200=A35),1),""),"") | J35: =IF(33<=Tenure,IF(H35=0,0,IF(AND(I35<>"",I35<>0,I35<C35),MIN(F35,MAX(0,H35-K35)-IFERROR(MIN(MAX(0,(MAX(0,H35-K35)-F35)/(1-MAX(0,C35-I35)*(AnnualRate/100))),E35,MAX(0,H35-K35)),0)),MIN(F35,MAX(0,H35-K35)))),"") | K35: =IF(33<=Tenure,IF(H35=0,0,MIN(E35,MAX(0,MAX(0,H35-K35)-L35))),"") | L35: =IF(33<=Tenure,MAX(0,F35+G35+J35-K35-L35-M35),"") | M35: =IF(33<=Tenure,IF(33=Tenure,0,MAX(0,E35-M35)),"") | N35: =IF(33>Tenure,"",IF(AND(H35>0,H35>=F35+G35+J35),"Paid",IF(AND(H35>0,H35<F35+G35),"Partial",IF(AND(H35=0,TODAY()>C35),"Overdue","Pending"))))
A36: =IF(34<=Tenure,34,"") | B36: =IF(34<=Tenure,C35,"") | C36: =IF(34<=Tenure,WORKDAY.INTL(EDATE(FirstPayDate,33)-1,1,1,ArmenianHolidays),"") | D36: =IF(34<=Tenure,IF(34=Tenure,C36-C35+1,C36-C35),"") | E36: =IF(34<=Tenure,O35,"") | F36: =IF(34<=Tenure,E36*D36*(AnnualRate/100),"") | G36: =IF(34<=Tenure,IF(34=Tenure,E36,EMI-F36),"") | H36: =IF(34<=Tenure,IFERROR(SUMIFS(Payments!$C:$C,Payments!$B:$B,A36),0),"") | I36: =IF(34<=Tenure,IFERROR(AGGREGATE(15,6,Payments!$A$3:$A$200/(Payments!$B$3:$B$200=A36),1),""),"") | J36: =IF(34<=Tenure,IF(H36=0,0,IF(AND(I36<>"",I36<>0,I36<C36),MIN(F36,MAX(0,H36-K36)-IFERROR(MIN(MAX(0,(MAX(0,H36-K36)-F36)/(1-MAX(0,C36-I36)*(AnnualRate/100))),E36,MAX(0,H36-K36)),0)),MIN(F36,MAX(0,H36-K36)))),"") | K36: =IF(34<=Tenure,IF(H36=0,0,MIN(E36,MAX(0,MAX(0,H36-K36)-L36))),"") | L36: =IF(34<=Tenure,MAX(0,F36+G36+J36-K36-L36-M36),"") | M36: =IF(34<=Tenure,IF(34=Tenure,0,MAX(0,E36-M36)),"") | N36: =IF(34>Tenure,"",IF(AND(H36>0,H36>=F36+G36+J36),"Paid",IF(AND(H36>0,H36<F36+G36),"Partial",IF(AND(H36=0,TODAY()>C36),"Overdue","Pending"))))
A37: =IF(35<=Tenure,35,"") | B37: =IF(35<=Tenure,C36,"") | C37: =IF(35<=Tenure,WORKDAY.INTL(EDATE(FirstPayDate,34)-1,1,1,ArmenianHolidays),"") | D37: =IF(35<=Tenure,IF(35=Tenure,C37-C36+1,C37-C36),"") | E37: =IF(35<=Tenure,O36,"") | F37: =IF(35<=Tenure,E37*D37*(AnnualRate/100),"") | G37: =IF(35<=Tenure,IF(35=Tenure,E37,EMI-F37),"") | H37: =IF(35<=Tenure,IFERROR(SUMIFS(Payments!$C:$C,Payments!$B:$B,A37),0),"") | I37: =IF(35<=Tenure,IFERROR(AGGREGATE(15,6,Payments!$A$3:$A$200/(Payments!$B$3:$B$200=A37),1),""),"") | J37: =IF(35<=Tenure,IF(H37=0,0,IF(AND(I37<>"",I37<>0,I37<C37),MIN(F37,MAX(0,H37-K37)-IFERROR(MIN(MAX(0,(MAX(0,H37-K37)-F37)/(1-MAX(0,C37-I37)*(AnnualRate/100))),E37,MAX(0,H37-K37)),0)),MIN(F37,MAX(0,H37-K37)))),"") | K37: =IF(35<=Tenure,IF(H37=0,0,MIN(E37,MAX(0,MAX(0,H37-K37)-L37))),"") | L37: =IF(35<=Tenure,MAX(0,F37+G37+J37-K37-L37-M37),"") | M37: =IF(35<=Tenure,IF(35=Tenure,0,MAX(0,E37-M37)),"") | N37: =IF(35>Tenure,"",IF(AND(H37>0,H37>=F37+G37+J37),"Paid",IF(AND(H37>0,H37<F37+G37),"Partial",IF(AND(H37=0,TODAY()>C37),"Overdue","Pending"))))
A38: =IF(36<=Tenure,36,"") | B38: =IF(36<=Tenure,C37,"") | C38: =IF(36<=Tenure,WORKDAY.INTL(EDATE(FirstPayDate,35)-1,1,1,ArmenianHolidays),"") | D38: =IF(36<=Tenure,IF(36=Tenure,C38-C37+1,C38-C37),"") | E38: =IF(36<=Tenure,O37,"") | F38: =IF(36<=Tenure,E38*D38*(AnnualRate/100),"") | G38: =IF(36<=Tenure,IF(36=Tenure,E38,EMI-F38),"") | H38: =IF(36<=Tenure,IFERROR(SUMIFS(Payments!$C:$C,Payments!$B:$B,A38),0),"") | I38: =IF(36<=Tenure,IFERROR(AGGREGATE(15,6,Payments!$A$3:$A$200/(Payments!$B$3:$B$200=A38),1),""),"") | J38: =IF(36<=Tenure,IF(H38=0,0,IF(AND(I38<>"",I38<>0,I38<C38),MIN(F38,MAX(0,H38-K38)-IFERROR(MIN(MAX(0,(MAX(0,H38-K38)-F38)/(1-MAX(0,C38-I38)*(AnnualRate/100))),E38,MAX(0,H38-K38)),0)),MIN(F38,MAX(0,H38-K38)))),"") | K38: =IF(36<=Tenure,IF(H38=0,0,MIN(E38,MAX(0,MAX(0,H38-K38)-L38))),"") | L38: =IF(36<=Tenure,MAX(0,F38+G38+J38-K38-L38-M38),"") | M38: =IF(36<=Tenure,IF(36=Tenure,0,MAX(0,E38-M38)),"") | N38: =IF(36>Tenure,"",IF(AND(H38>0,H38>=F38+G38+J38),"Paid",IF(AND(H38>0,H38<F38+G38),"Partial",IF(AND(H38=0,TODAY()>C38),"Overdue","Pending"))))
A39: =IF(37<=Tenure,37,"") | B39: =IF(37<=Tenure,C38,"") | C39: =IF(37<=Tenure,WORKDAY.INTL(EDATE(FirstPayDate,36)-1,1,1,ArmenianHolidays),"") | D39: =IF(37<=Tenure,IF(37=Tenure,C39-C38+1,C39-C38),"") | E39: =IF(37<=Tenure,O38,"") | F39: =IF(37<=Tenure,E39*D39*(AnnualRate/100),"") | G39: =IF(37<=Tenure,IF(37=Tenure,E39,EMI-F39),"") | H39: =IF(37<=Tenure,IFERROR(SUMIFS(Payments!$C:$C,Payments!$B:$B,A39),0),"") | I39: =IF(37<=Tenure,IFERROR(AGGREGATE(15,6,Payments!$A$3:$A$200/(Payments!$B$3:$B$200=A39),1),""),"") | J39: =IF(37<=Tenure,IF(H39=0,0,IF(AND(I39<>"",I39<>0,I39<C39),MIN(F39,MAX(0,H39-K39)-IFERROR(MIN(MAX(0,(MAX(0,H39-K39)-F39)/(1-MAX(0,C39-I39)*(AnnualRate/100))),E39,MAX(0,H39-K39)),0)),MIN(F39,MAX(0,H39-K39)))),"") | K39: =IF(37<=Tenure,IF(H39=0,0,MIN(E39,MAX(0,MAX(0,H39-K39)-L39))),"") | L39: =IF(37<=Tenure,MAX(0,F39+G39+J39-K39-L39-M39),"") | M39: =IF(37<=Tenure,IF(37=Tenure,0,MAX(0,E39-M39)),"") | N39: =IF(37>Tenure,"",IF(AND(H39>0,H39>=F39+G39+J39),"Paid",IF(AND(H39>0,H39<F39+G39),"Partial",IF(AND(H39=0,TODAY()>C39),"Overdue","Pending"))))
A40: =IF(38<=Tenure,38,"") | B40: =IF(38<=Tenure,C39,"") | C40: =IF(38<=Tenure,WORKDAY.INTL(EDATE(FirstPayDate,37)-1,1,1,ArmenianHolidays),"") | D40: =IF(38<=Tenure,IF(38=Tenure,C40-C39+1,C40-C39),"") | E40: =IF(38<=Tenure,O39,"") | F40: =IF(38<=Tenure,E40*D40*(AnnualRate/100),"") | G40: =IF(38<=Tenure,IF(38=Tenure,E40,EMI-F40),"") | H40: =IF(38<=Tenure,IFERROR(SUMIFS(Payments!$C:$C,Payments!$B:$B,A40),0),"") | I40: =IF(38<=Tenure,IFERROR(AGGREGATE(15,6,Payments!$A$3:$A$200/(Payments!$B$3:$B$200=A40),1),""),"") | J40: =IF(38<=Tenure,IF(H40=0,0,IF(AND(I40<>"",I40<>0,I40<C40),MIN(F40,MAX(0,H40-K40)-IFERROR(MIN(MAX(0,(MAX(0,H40-K40)-F40)/(1-MAX(0,C40-I40)*(AnnualRate/100))),E40,MAX(0,H40-K40)),0)),MIN(F40,MAX(0,H40-K40)))),"") | K40: =IF(38<=Tenure,IF(H40=0,0,MIN(E40,MAX(0,MAX(0,H40-K40)-L40))),"") | L40: =IF(38<=Tenure,MAX(0,F40+G40+J40-K40-L40-M40),"") | M40: =IF(38<=Tenure,IF(38=Tenure,0,MAX(0,E40-M40)),"") | N40: =IF(38>Tenure,"",IF(AND(H40>0,H40>=F40+G40+J40),"Paid",IF(AND(H40>0,H40<F40+G40),"Partial",IF(AND(H40=0,TODAY()>C40),"Overdue","Pending"))))
A41: =IF(39<=Tenure,39,"") | B41: =IF(39<=Tenure,C40,"") | C41: =IF(39<=Tenure,WORKDAY.INTL(EDATE(FirstPayDate,38)-1,1,1,ArmenianHolidays),"") | D41: =IF(39<=Tenure,IF(39=Tenure,C41-C40+1,C41-C40),"") | E41: =IF(39<=Tenure,O40,"") | F41: =IF(39<=Tenure,E41*D41*(AnnualRate/100),"") | G41: =IF(39<=Tenure,IF(39=Tenure,E41,EMI-F41),"") | H41: =IF(39<=Tenure,IFERROR(SUMIFS(Payments!$C:$C,Payments!$B:$B,A41),0),"") | I41: =IF(39<=Tenure,IFERROR(AGGREGATE(15,6,Payments!$A$3:$A$200/(Payments!$B$3:$B$200=A41),1),""),"") | J41: =IF(39<=Tenure,IF(H41=0,0,IF(AND(I41<>"",I41<>0,I41<C41),MIN(F41,MAX(0,H41-K41)-IFERROR(MIN(MAX(0,(MAX(0,H41-K41)-F41)/(1-MAX(0,C41-I41)*(AnnualRate/100))),E41,MAX(0,H41-K41)),0)),MIN(F41,MAX(0,H41-K41)))),"") | K41: =IF(39<=Tenure,IF(H41=0,0,MIN(E41,MAX(0,MAX(0,H41-K41)-L41))),"") | L41: =IF(39<=Tenure,MAX(0,F41+G41+J41-K41-L41-M41),"") | M41: =IF(39<=Tenure,IF(39=Tenure,0,MAX(0,E41-M41)),"") | N41: =IF(39>Tenure,"",IF(AND(H41>0,H41>=F41+G41+J41),"Paid",IF(AND(H41>0,H41<F41+G41),"Partial",IF(AND(H41=0,TODAY()>C41),"Overdue","Pending"))))
A42: =IF(40<=Tenure,40,"") | B42: =IF(40<=Tenure,C41,"") | C42: =IF(40<=Tenure,WORKDAY.INTL(EDATE(FirstPayDate,39)-1,1,1,ArmenianHolidays),"") | D42: =IF(40<=Tenure,IF(40=Tenure,C42-C41+1,C42-C41),"") | E42: =IF(40<=Tenure,O41,"") | F42: =IF(40<=Tenure,E42*D42*(AnnualRate/100),"") | G42: =IF(40<=Tenure,IF(40=Tenure,E42,EMI-F42),"") | H42: =IF(40<=Tenure,IFERROR(SUMIFS(Payments!$C:$C,Payments!$B:$B,A42),0),"") | I42: =IF(40<=Tenure,IFERROR(AGGREGATE(15,6,Payments!$A$3:$A$200/(Payments!$B$3:$B$200=A42),1),""),"") | J42: =IF(40<=Tenure,IF(H42=0,0,IF(AND(I42<>"",I42<>0,I42<C42),MIN(F42,MAX(0,H42-K42)-IFERROR(MIN(MAX(0,(MAX(0,H42-K42)-F42)/(1-MAX(0,C42-I42)*(AnnualRate/100))),E42,MAX(0,H42-K42)),0)),MIN(F42,MAX(0,H42-K42)))),"") | K42: =IF(40<=Tenure,IF(H42=0,0,MIN(E42,MAX(0,MAX(0,H42-K42)-L42))),"") | L42: =IF(40<=Tenure,MAX(0,F42+G42+J42-K42-L42-M42),"") | M42: =IF(40<=Tenure,IF(40=Tenure,0,MAX(0,E42-M42)),"") | N42: =IF(40>Tenure,"",IF(AND(H42>0,H42>=F42+G42+J42),"Paid",IF(AND(H42>0,H42<F42+G42),"Partial",IF(AND(H42=0,TODAY()>C42),"Overdue","Pending"))))
A43: =IF(41<=Tenure,41,"") | B43: =IF(41<=Tenure,C42,"") | C43: =IF(41<=Tenure,WORKDAY.INTL(EDATE(FirstPayDate,40)-1,1,1,ArmenianHolidays),"") | D43: =IF(41<=Tenure,IF(41=Tenure,C43-C42+1,C43-C42),"") | E43: =IF(41<=Tenure,O42,"") | F43: =IF(41<=Tenure,E43*D43*(AnnualRate/100),"") | G43: =IF(41<=Tenure,IF(41=Tenure,E43,EMI-F43),"") | H43: =IF(41<=Tenure,IFERROR(SUMIFS(Payments!$C:$C,Payments!$B:$B,A43),0),"") | I43: =IF(41<=Tenure,IFERROR(AGGREGATE(15,6,Payments!$A$3:$A$200/(Payments!$B$3:$B$200=A43),1),""),"") | J43: =IF(41<=Tenure,IF(H43=0,0,IF(AND(I43<>"",I43<>0,I43<C43),MIN(F43,MAX(0,H43-K43)-IFERROR(MIN(MAX(0,(MAX(0,H43-K43)-F43)/(1-MAX(0,C43-I43)*(AnnualRate/100))),E43,MAX(0,H43-K43)),0)),MIN(F43,MAX(0,H43-K43)))),"") | K43: =IF(41<=Tenure,IF(H43=0,0,MIN(E43,MAX(0,MAX(0,H43-K43)-L43))),"") | L43: =IF(41<=Tenure,MAX(0,F43+G43+J43-K43-L43-M43),"") | M43: =IF(41<=Tenure,IF(41=Tenure,0,MAX(0,E43-M43)),"") | N43: =IF(41>Tenure,"",IF(AND(H43>0,H43>=F43+G43+J43),"Paid",IF(AND(H43>0,H43<F43+G43),"Partial",IF(AND(H43=0,TODAY()>C43),"Overdue","Pending"))))
A44: =IF(42<=Tenure,42,"") | B44: =IF(42<=Tenure,C43,"") | C44: =IF(42<=Tenure,WORKDAY.INTL(EDATE(FirstPayDate,41)-1,1,1,ArmenianHolidays),"") | D44: =IF(42<=Tenure,IF(42=Tenure,C44-C43+1,C44-C43),"") | E44: =IF(42<=Tenure,O43,"") | F44: =IF(42<=Tenure,E44*D44*(AnnualRate/100),"") | G44: =IF(42<=Tenure,IF(42=Tenure,E44,EMI-F44),"") | H44: =IF(42<=Tenure,IFERROR(SUMIFS(Payments!$C:$C,Payments!$B:$B,A44),0),"") | I44: =IF(42<=Tenure,IFERROR(AGGREGATE(15,6,Payments!$A$3:$A$200/(Payments!$B$3:$B$200=A44),1),""),"") | J44: =IF(42<=Tenure,IF(H44=0,0,IF(AND(I44<>"",I44<>0,I44<C44),MIN(F44,MAX(0,H44-K44)-IFERROR(MIN(MAX(0,(MAX(0,H44-K44)-F44)/(1-MAX(0,C44-I44)*(AnnualRate/100))),E44,MAX(0,H44-K44)),0)),MIN(F44,MAX(0,H44-K44)))),"") | K44: =IF(42<=Tenure,IF(H44=0,0,MIN(E44,MAX(0,MAX(0,H44-K44)-L44))),"") | L44: =IF(42<=Tenure,MAX(0,F44+G44+J44-K44-L44-M44),"") | M44: =IF(42<=Tenure,IF(42=Tenure,0,MAX(0,E44-M44)),"") | N44: =IF(42>Tenure,"",IF(AND(H44>0,H44>=F44+G44+J44),"Paid",IF(AND(H44>0,H44<F44+G44),"Partial",IF(AND(H44=0,TODAY()>C44),"Overdue","Pending"))))
A45: =IF(43<=Tenure,43,"") | B45: =IF(43<=Tenure,C44,"") | C45: =IF(43<=Tenure,WORKDAY.INTL(EDATE(FirstPayDate,42)-1,1,1,ArmenianHolidays),"") | D45: =IF(43<=Tenure,IF(43=Tenure,C45-C44+1,C45-C44),"") | E45: =IF(43<=Tenure,O44,"") | F45: =IF(43<=Tenure,E45*D45*(AnnualRate/100),"") | G45: =IF(43<=Tenure,IF(43=Tenure,E45,EMI-F45),"") | H45: =IF(43<=Tenure,IFERROR(SUMIFS(Payments!$C:$C,Payments!$B:$B,A45),0),"") | I45: =IF(43<=Tenure,IFERROR(AGGREGATE(15,6,Payments!$A$3:$A$200/(Payments!$B$3:$B$200=A45),1),""),"") | J45: =IF(43<=Tenure,IF(H45=0,0,IF(AND(I45<>"",I45<>0,I45<C45),MIN(F45,MAX(0,H45-K45)-IFERROR(MIN(MAX(0,(MAX(0,H45-K45)-F45)/(1-MAX(0,C45-I45)*(AnnualRate/100))),E45,MAX(0,H45-K45)),0)),MIN(F45,MAX(0,H45-K45)))),"") | K45: =IF(43<=Tenure,IF(H45=0,0,MIN(E45,MAX(0,MAX(0,H45-K45)-L45))),"") | L45: =IF(43<=Tenure,MAX(0,F45+G45+J45-K45-L45-M45),"") | M45: =IF(43<=Tenure,IF(43=Tenure,0,MAX(0,E45-M45)),"") | N45: =IF(43>Tenure,"",IF(AND(H45>0,H45>=F45+G45+J45),"Paid",IF(AND(H45>0,H45<F45+G45),"Partial",IF(AND(H45=0,TODAY()>C45),"Overdue","Pending"))))
A46: =IF(44<=Tenure,44,"") | B46: =IF(44<=Tenure,C45,"") | C46: =IF(44<=Tenure,WORKDAY.INTL(EDATE(FirstPayDate,43)-1,1,1,ArmenianHolidays),"") | D46: =IF(44<=Tenure,IF(44=Tenure,C46-C45+1,C46-C45),"") | E46: =IF(44<=Tenure,O45,"") | F46: =IF(44<=Tenure,E46*D46*(AnnualRate/100),"") | G46: =IF(44<=Tenure,IF(44=Tenure,E46,EMI-F46),"") | H46: =IF(44<=Tenure,IFERROR(SUMIFS(Payments!$C:$C,Payments!$B:$B,A46),0),"") | I46: =IF(44<=Tenure,IFERROR(AGGREGATE(15,6,Payments!$A$3:$A$200/(Payments!$B$3:$B$200=A46),1),""),"") | J46: =IF(44<=Tenure,IF(H46=0,0,IF(AND(I46<>"",I46<>0,I46<C46),MIN(F46,MAX(0,H46-K46)-IFERROR(MIN(MAX(0,(MAX(0,H46-K46)-F46)/(1-MAX(0,C46-I46)*(AnnualRate/100))),E46,MAX(0,H46-K46)),0)),MIN(F46,MAX(0,H46-K46)))),"") | K46: =IF(44<=Tenure,IF(H46=0,0,MIN(E46,MAX(0,MAX(0,H46-K46)-L46))),"") | L46: =IF(44<=Tenure,MAX(0,F46+G46+J46-K46-L46-M46),"") | M46: =IF(44<=Tenure,IF(44=Tenure,0,MAX(0,E46-M46)),"") | N46: =IF(44>Tenure,"",IF(AND(H46>0,H46>=F46+G46+J46),"Paid",IF(AND(H46>0,H46<F46+G46),"Partial",IF(AND(H46=0,TODAY()>C46),"Overdue","Pending"))))
A47: =IF(45<=Tenure,45,"") | B47: =IF(45<=Tenure,C46,"") | C47: =IF(45<=Tenure,WORKDAY.INTL(EDATE(FirstPayDate,44)-1,1,1,ArmenianHolidays),"") | D47: =IF(45<=Tenure,IF(45=Tenure,C47-C46+1,C47-C46),"") | E47: =IF(45<=Tenure,O46,"") | F47: =IF(45<=Tenure,E47*D47*(AnnualRate/100),"") | G47: =IF(45<=Tenure,IF(45=Tenure,E47,EMI-F47),"") | H47: =IF(45<=Tenure,IFERROR(SUMIFS(Payments!$C:$C,Payments!$B:$B,A47),0),"") | I47: =IF(45<=Tenure,IFERROR(AGGREGATE(15,6,Payments!$A$3:$A$200/(Payments!$B$3:$B$200=A47),1),""),"") | J47: =IF(45<=Tenure,IF(H47=0,0,IF(AND(I47<>"",I47<>0,I47<C47),MIN(F47,MAX(0,H47-K47)-IFERROR(MIN(MAX(0,(MAX(0,H47-K47)-F47)/(1-MAX(0,C47-I47)*(AnnualRate/100))),E47,MAX(0,H47-K47)),0)),MIN(F47,MAX(0,H47-K47)))),"") | K47: =IF(45<=Tenure,IF(H47=0,0,MIN(E47,MAX(0,MAX(0,H47-K47)-L47))),"") | L47: =IF(45<=Tenure,MAX(0,F47+G47+J47-K47-L47-M47),"") | M47: =IF(45<=Tenure,IF(45=Tenure,0,MAX(0,E47-M47)),"") | N47: =IF(45>Tenure,"",IF(AND(H47>0,H47>=F47+G47+J47),"Paid",IF(AND(H47>0,H47<F47+G47),"Partial",IF(AND(H47=0,TODAY()>C47),"Overdue","Pending"))))
A48: =IF(46<=Tenure,46,"") | B48: =IF(46<=Tenure,C47,"") | C48: =IF(46<=Tenure,WORKDAY.INTL(EDATE(FirstPayDate,45)-1,1,1,ArmenianHolidays),"") | D48: =IF(46<=Tenure,IF(46=Tenure,C48-C47+1,C48-C47),"") | E48: =IF(46<=Tenure,O47,"") | F48: =IF(46<=Tenure,E48*D48*(AnnualRate/100),"") | G48: =IF(46<=Tenure,IF(46=Tenure,E48,EMI-F48),"") | H48: =IF(46<=Tenure,IFERROR(SUMIFS(Payments!$C:$C,Payments!$B:$B,A48),0),"") | I48: =IF(46<=Tenure,IFERROR(AGGREGATE(15,6,Payments!$A$3:$A$200/(Payments!$B$3:$B$200=A48),1),""),"") | J48: =IF(46<=Tenure,IF(H48=0,0,IF(AND(I48<>"",I48<>0,I48<C48),MIN(F48,MAX(0,H48-K48)-IFERROR(MIN(MAX(0,(MAX(0,H48-K48)-F48)/(1-MAX(0,C48-I48)*(AnnualRate/100))),E48,MAX(0,H48-K48)),0)),MIN(F48,MAX(0,H48-K48)))),"") | K48: =IF(46<=Tenure,IF(H48=0,0,MIN(E48,MAX(0,MAX(0,H48-K48)-L48))),"") | L48: =IF(46<=Tenure,MAX(0,F48+G48+J48-K48-L48-M48),"") | M48: =IF(46<=Tenure,IF(46=Tenure,0,MAX(0,E48-M48)),"") | N48: =IF(46>Tenure,"",IF(AND(H48>0,H48>=F48+G48+J48),"Paid",IF(AND(H48>0,H48<F48+G48),"Partial",IF(AND(H48=0,TODAY()>C48),"Overdue","Pending"))))
A49: =IF(47<=Tenure,47,"") | B49: =IF(47<=Tenure,C48,"") | C49: =IF(47<=Tenure,WORKDAY.INTL(EDATE(FirstPayDate,46)-1,1,1,ArmenianHolidays),"") | D49: =IF(47<=Tenure,IF(47=Tenure,C49-C48+1,C49-C48),"") | E49: =IF(47<=Tenure,O48,"") | F49: =IF(47<=Tenure,E49*D49*(AnnualRate/100),"") | G49: =IF(47<=Tenure,IF(47=Tenure,E49,EMI-F49),"") | H49: =IF(47<=Tenure,IFERROR(SUMIFS(Payments!$C:$C,Payments!$B:$B,A49),0),"") | I49: =IF(47<=Tenure,IFERROR(AGGREGATE(15,6,Payments!$A$3:$A$200/(Payments!$B$3:$B$200=A49),1),""),"") | J49: =IF(47<=Tenure,IF(H49=0,0,IF(AND(I49<>"",I49<>0,I49<C49),MIN(F49,MAX(0,H49-K49)-IFERROR(MIN(MAX(0,(MAX(0,H49-K49)-F49)/(1-MAX(0,C49-I49)*(AnnualRate/100))),E49,MAX(0,H49-K49)),0)),MIN(F49,MAX(0,H49-K49)))),"") | K49: =IF(47<=Tenure,IF(H49=0,0,MIN(E49,MAX(0,MAX(0,H49-K49)-L49))),"") | L49: =IF(47<=Tenure,MAX(0,F49+G49+J49-K49-L49-M49),"") | M49: =IF(47<=Tenure,IF(47=Tenure,0,MAX(0,E49-M49)),"") | N49: =IF(47>Tenure,"",IF(AND(H49>0,H49>=F49+G49+J49),"Paid",IF(AND(H49>0,H49<F49+G49),"Partial",IF(AND(H49=0,TODAY()>C49),"Overdue","Pending"))))
A50: =IF(48<=Tenure,48,"") | B50: =IF(48<=Tenure,C49,"") | C50: =IF(48<=Tenure,WORKDAY.INTL(EDATE(FirstPayDate,47)-1,1,1,ArmenianHolidays),"") | D50: =IF(48<=Tenure,IF(48=Tenure,C50-C49+1,C50-C49),"") | E50: =IF(48<=Tenure,O49,"") | F50: =IF(48<=Tenure,E50*D50*(AnnualRate/100),"") | G50: =IF(48<=Tenure,IF(48=Tenure,E50,EMI-F50),"") | H50: =IF(48<=Tenure,IFERROR(SUMIFS(Payments!$C:$C,Payments!$B:$B,A50),0),"") | I50: =IF(48<=Tenure,IFERROR(AGGREGATE(15,6,Payments!$A$3:$A$200/(Payments!$B$3:$B$200=A50),1),""),"") | J50: =IF(48<=Tenure,IF(H50=0,0,IF(AND(I50<>"",I50<>0,I50<C50),MIN(F50,MAX(0,H50-K50)-IFERROR(MIN(MAX(0,(MAX(0,H50-K50)-F50)/(1-MAX(0,C50-I50)*(AnnualRate/100))),E50,MAX(0,H50-K50)),0)),MIN(F50,MAX(0,H50-K50)))),"") | K50: =IF(48<=Tenure,IF(H50=0,0,MIN(E50,MAX(0,MAX(0,H50-K50)-L50))),"") | L50: =IF(48<=Tenure,MAX(0,F50+G50+J50-K50-L50-M50),"") | M50: =IF(48<=Tenure,IF(48=Tenure,0,MAX(0,E50-M50)),"") | N50: =IF(48>Tenure,"",IF(AND(H50>0,H50>=F50+G50+J50),"Paid",IF(AND(H50>0,H50<F50+G50),"Partial",IF(AND(H50=0,TODAY()>C50),"Overdue","Pending"))))
A51: =IF(49<=Tenure,49,"") | B51: =IF(49<=Tenure,C50,"") | C51: =IF(49<=Tenure,WORKDAY.INTL(EDATE(FirstPayDate,48)-1,1,1,ArmenianHolidays),"") | D51: =IF(49<=Tenure,IF(49=Tenure,C51-C50+1,C51-C50),"") | E51: =IF(49<=Tenure,O50,"") | F51: =IF(49<=Tenure,E51*D51*(AnnualRate/100),"") | G51: =IF(49<=Tenure,IF(49=Tenure,E51,EMI-F51),"") | H51: =IF(49<=Tenure,IFERROR(SUMIFS(Payments!$C:$C,Payments!$B:$B,A51),0),"") | I51: =IF(49<=Tenure,IFERROR(AGGREGATE(15,6,Payments!$A$3:$A$200/(Payments!$B$3:$B$200=A51),1),""),"") | J51: =IF(49<=Tenure,IF(H51=0,0,IF(AND(I51<>"",I51<>0,I51<C51),MIN(F51,MAX(0,H51-K51)-IFERROR(MIN(MAX(0,(MAX(0,H51-K51)-F51)/(1-MAX(0,C51-I51)*(AnnualRate/100))),E51,MAX(0,H51-K51)),0)),MIN(F51,MAX(0,H51-K51)))),"") | K51: =IF(49<=Tenure,IF(H51=0,0,MIN(E51,MAX(0,MAX(0,H51-K51)-L51))),"") | L51: =IF(49<=Tenure,MAX(0,F51+G51+J51-K51-L51-M51),"") | M51: =IF(49<=Tenure,IF(49=Tenure,0,MAX(0,E51-M51)),"") | N51: =IF(49>Tenure,"",IF(AND(H51>0,H51>=F51+G51+J51),"Paid",IF(AND(H51>0,H51<F51+G51),"Partial",IF(AND(H51=0,TODAY()>C51),"Overdue","Pending"))))
A52: =IF(50<=Tenure,50,"") | B52: =IF(50<=Tenure,C51,"") | C52: =IF(50<=Tenure,WORKDAY.INTL(EDATE(FirstPayDate,49)-1,1,1,ArmenianHolidays),"") | D52: =IF(50<=Tenure,IF(50=Tenure,C52-C51+1,C52-C51),"") | E52: =IF(50<=Tenure,O51,"") | F52: =IF(50<=Tenure,E52*D52*(AnnualRate/100),"") | G52: =IF(50<=Tenure,IF(50=Tenure,E52,EMI-F52),"") | H52: =IF(50<=Tenure,IFERROR(SUMIFS(Payments!$C:$C,Payments!$B:$B,A52),0),"") | I52: =IF(50<=Tenure,IFERROR(AGGREGATE(15,6,Payments!$A$3:$A$200/(Payments!$B$3:$B$200=A52),1),""),"") | J52: =IF(50<=Tenure,IF(H52=0,0,IF(AND(I52<>"",I52<>0,I52<C52),MIN(F52,MAX(0,H52-K52)-IFERROR(MIN(MAX(0,(MAX(0,H52-K52)-F52)/(1-MAX(0,C52-I52)*(AnnualRate/100))),E52,MAX(0,H52-K52)),0)),MIN(F52,MAX(0,H52-K52)))),"") | K52: =IF(50<=Tenure,IF(H52=0,0,MIN(E52,MAX(0,MAX(0,H52-K52)-L52))),"") | L52: =IF(50<=Tenure,MAX(0,F52+G52+J52-K52-L52-M52),"") | M52: =IF(50<=Tenure,IF(50=Tenure,0,MAX(0,E52-M52)),"") | N52: =IF(50>Tenure,"",IF(AND(H52>0,H52>=F52+G52+J52),"Paid",IF(AND(H52>0,H52<F52+G52),"Partial",IF(AND(H52=0,TODAY()>C52),"Overdue","Pending"))))
A53: =IF(51<=Tenure,51,"") | B53: =IF(51<=Tenure,C52,"") | C53: =IF(51<=Tenure,WORKDAY.INTL(EDATE(FirstPayDate,50)-1,1,1,ArmenianHolidays),"") | D53: =IF(51<=Tenure,IF(51=Tenure,C53-C52+1,C53-C52),"") | E53: =IF(51<=Tenure,O52,"") | F53: =IF(51<=Tenure,E53*D53*(AnnualRate/100),"") | G53: =IF(51<=Tenure,IF(51=Tenure,E53,EMI-F53),"") | H53: =IF(51<=Tenure,IFERROR(SUMIFS(Payments!$C:$C,Payments!$B:$B,A53),0),"") | I53: =IF(51<=Tenure,IFERROR(AGGREGATE(15,6,Payments!$A$3:$A$200/(Payments!$B$3:$B$200=A53),1),""),"") | J53: =IF(51<=Tenure,IF(H53=0,0,IF(AND(I53<>"",I53<>0,I53<C53),MIN(F53,MAX(0,H53-K53)-IFERROR(MIN(MAX(0,(MAX(0,H53-K53)-F53)/(1-MAX(0,C53-I53)*(AnnualRate/100))),E53,MAX(0,H53-K53)),0)),MIN(F53,MAX(0,H53-K53)))),"") | K53: =IF(51<=Tenure,IF(H53=0,0,MIN(E53,MAX(0,MAX(0,H53-K53)-L53))),"") | L53: =IF(51<=Tenure,MAX(0,F53+G53+J53-K53-L53-M53),"") | M53: =IF(51<=Tenure,IF(51=Tenure,0,MAX(0,E53-M53)),"") | N53: =IF(51>Tenure,"",IF(AND(H53>0,H53>=F53+G53+J53),"Paid",IF(AND(H53>0,H53<F53+G53),"Partial",IF(AND(H53=0,TODAY()>C53),"Overdue","Pending"))))
A54: =IF(52<=Tenure,52,"") | B54: =IF(52<=Tenure,C53,"") | C54: =IF(52<=Tenure,WORKDAY.INTL(EDATE(FirstPayDate,51)-1,1,1,ArmenianHolidays),"") | D54: =IF(52<=Tenure,IF(52=Tenure,C54-C53+1,C54-C53),"") | E54: =IF(52<=Tenure,O53,"") | F54: =IF(52<=Tenure,E54*D54*(AnnualRate/100),"") | G54: =IF(52<=Tenure,IF(52=Tenure,E54,EMI-F54),"") | H54: =IF(52<=Tenure,IFERROR(SUMIFS(Payments!$C:$C,Payments!$B:$B,A54),0),"") | I54: =IF(52<=Tenure,IFERROR(AGGREGATE(15,6,Payments!$A$3:$A$200/(Payments!$B$3:$B$200=A54),1),""),"") | J54: =IF(52<=Tenure,IF(H54=0,0,IF(AND(I54<>"",I54<>0,I54<C54),MIN(F54,MAX(0,H54-K54)-IFERROR(MIN(MAX(0,(MAX(0,H54-K54)-F54)/(1-MAX(0,C54-I54)*(AnnualRate/100))),E54,MAX(0,H54-K54)),0)),MIN(F54,MAX(0,H54-K54)))),"") | K54: =IF(52<=Tenure,IF(H54=0,0,MIN(E54,MAX(0,MAX(0,H54-K54)-L54))),"") | L54: =IF(52<=Tenure,MAX(0,F54+G54+J54-K54-L54-M54),"") | M54: =IF(52<=Tenure,IF(52=Tenure,0,MAX(0,E54-M54)),"") | N54: =IF(52>Tenure,"",IF(AND(H54>0,H54>=F54+G54+J54),"Paid",IF(AND(H54>0,H54<F54+G54),"Partial",IF(AND(H54=0,TODAY()>C54),"Overdue","Pending"))))
A55: =IF(53<=Tenure,53,"") | B55: =IF(53<=Tenure,C54,"") | C55: =IF(53<=Tenure,WORKDAY.INTL(EDATE(FirstPayDate,52)-1,1,1,ArmenianHolidays),"") | D55: =IF(53<=Tenure,IF(53=Tenure,C55-C54+1,C55-C54),"") | E55: =IF(53<=Tenure,O54,"") | F55: =IF(53<=Tenure,E55*D55*(AnnualRate/100),"") | G55: =IF(53<=Tenure,IF(53=Tenure,E55,EMI-F55),"") | H55: =IF(53<=Tenure,IFERROR(SUMIFS(Payments!$C:$C,Payments!$B:$B,A55),0),"") | I55: =IF(53<=Tenure,IFERROR(AGGREGATE(15,6,Payments!$A$3:$A$200/(Payments!$B$3:$B$200=A55),1),""),"") | J55: =IF(53<=Tenure,IF(H55=0,0,IF(AND(I55<>"",I55<>0,I55<C55),MIN(F55,MAX(0,H55-K55)-IFERROR(MIN(MAX(0,(MAX(0,H55-K55)-F55)/(1-MAX(0,C55-I55)*(AnnualRate/100))),E55,MAX(0,H55-K55)),0)),MIN(F55,MAX(0,H55-K55)))),"") | K55: =IF(53<=Tenure,IF(H55=0,0,MIN(E55,MAX(0,MAX(0,H55-K55)-L55))),"") | L55: =IF(53<=Tenure,MAX(0,F55+G55+J55-K55-L55-M55),"") | M55: =IF(53<=Tenure,IF(53=Tenure,0,MAX(0,E55-M55)),"") | N55: =IF(53>Tenure,"",IF(AND(H55>0,H55>=F55+G55+J55),"Paid",IF(AND(H55>0,H55<F55+G55),"Partial",IF(AND(H55=0,TODAY()>C55),"Overdue","Pending"))))
A56: =IF(54<=Tenure,54,"") | B56: =IF(54<=Tenure,C55,"") | C56: =IF(54<=Tenure,WORKDAY.INTL(EDATE(FirstPayDate,53)-1,1,1,ArmenianHolidays),"") | D56: =IF(54<=Tenure,IF(54=Tenure,C56-C55+1,C56-C55),"") | E56: =IF(54<=Tenure,O55,"") | F56: =IF(54<=Tenure,E56*D56*(AnnualRate/100),"") | G56: =IF(54<=Tenure,IF(54=Tenure,E56,EMI-F56),"") | H56: =IF(54<=Tenure,IFERROR(SUMIFS(Payments!$C:$C,Payments!$B:$B,A56),0),"") | I56: =IF(54<=Tenure,IFERROR(AGGREGATE(15,6,Payments!$A$3:$A$200/(Payments!$B$3:$B$200=A56),1),""),"") | J56: =IF(54<=Tenure,IF(H56=0,0,IF(AND(I56<>"",I56<>0,I56<C56),MIN(F56,MAX(0,H56-K56)-IFERROR(MIN(MAX(0,(MAX(0,H56-K56)-F56)/(1-MAX(0,C56-I56)*(AnnualRate/100))),E56,MAX(0,H56-K56)),0)),MIN(F56,MAX(0,H56-K56)))),"") | K56: =IF(54<=Tenure,IF(H56=0,0,MIN(E56,MAX(0,MAX(0,H56-K56)-L56))),"") | L56: =IF(54<=Tenure,MAX(0,F56+G56+J56-K56-L56-M56),"") | M56: =IF(54<=Tenure,IF(54=Tenure,0,MAX(0,E56-M56)),"") | N56: =IF(54>Tenure,"",IF(AND(H56>0,H56>=F56+G56+J56),"Paid",IF(AND(H56>0,H56<F56+G56),"Partial",IF(AND(H56=0,TODAY()>C56),"Overdue","Pending"))))
A57: =IF(55<=Tenure,55,"") | B57: =IF(55<=Tenure,C56,"") | C57: =IF(55<=Tenure,WORKDAY.INTL(EDATE(FirstPayDate,54)-1,1,1,ArmenianHolidays),"") | D57: =IF(55<=Tenure,IF(55=Tenure,C57-C56+1,C57-C56),"") | E57: =IF(55<=Tenure,O56,"") | F57: =IF(55<=Tenure,E57*D57*(AnnualRate/100),"") | G57: =IF(55<=Tenure,IF(55=Tenure,E57,EMI-F57),"") | H57: =IF(55<=Tenure,IFERROR(SUMIFS(Payments!$C:$C,Payments!$B:$B,A57),0),"") | I57: =IF(55<=Tenure,IFERROR(AGGREGATE(15,6,Payments!$A$3:$A$200/(Payments!$B$3:$B$200=A57),1),""),"") | J57: =IF(55<=Tenure,IF(H57=0,0,IF(AND(I57<>"",I57<>0,I57<C57),MIN(F57,MAX(0,H57-K57)-IFERROR(MIN(MAX(0,(MAX(0,H57-K57)-F57)/(1-MAX(0,C57-I57)*(AnnualRate/100))),E57,MAX(0,H57-K57)),0)),MIN(F57,MAX(0,H57-K57)))),"") | K57: =IF(55<=Tenure,IF(H57=0,0,MIN(E57,MAX(0,MAX(0,H57-K57)-L57))),"") | L57: =IF(55<=Tenure,MAX(0,F57+G57+J57-K57-L57-M57),"") | M57: =IF(55<=Tenure,IF(55=Tenure,0,MAX(0,E57-M57)),"") | N57: =IF(55>Tenure,"",IF(AND(H57>0,H57>=F57+G57+J57),"Paid",IF(AND(H57>0,H57<F57+G57),"Partial",IF(AND(H57=0,TODAY()>C57),"Overdue","Pending"))))
A58: =IF(56<=Tenure,56,"") | B58: =IF(56<=Tenure,C57,"") | C58: =IF(56<=Tenure,WORKDAY.INTL(EDATE(FirstPayDate,55)-1,1,1,ArmenianHolidays),"") | D58: =IF(56<=Tenure,IF(56=Tenure,C58-C57+1,C58-C57),"") | E58: =IF(56<=Tenure,O57,"") | F58: =IF(56<=Tenure,E58*D58*(AnnualRate/100),"") | G58: =IF(56<=Tenure,IF(56=Tenure,E58,EMI-F58),"") | H58: =IF(56<=Tenure,IFERROR(SUMIFS(Payments!$C:$C,Payments!$B:$B,A58),0),"") | I58: =IF(56<=Tenure,IFERROR(AGGREGATE(15,6,Payments!$A$3:$A$200/(Payments!$B$3:$B$200=A58),1),""),"") | J58: =IF(56<=Tenure,IF(H58=0,0,IF(AND(I58<>"",I58<>0,I58<C58),MIN(F58,MAX(0,H58-K58)-IFERROR(MIN(MAX(0,(MAX(0,H58-K58)-F58)/(1-MAX(0,C58-I58)*(AnnualRate/100))),E58,MAX(0,H58-K58)),0)),MIN(F58,MAX(0,H58-K58)))),"") | K58: =IF(56<=Tenure,IF(H58=0,0,MIN(E58,MAX(0,MAX(0,H58-K58)-L58))),"") | L58: =IF(56<=Tenure,MAX(0,F58+G58+J58-K58-L58-M58),"") | M58: =IF(56<=Tenure,IF(56=Tenure,0,MAX(0,E58-M58)),"") | N58: =IF(56>Tenure,"",IF(AND(H58>0,H58>=F58+G58+J58),"Paid",IF(AND(H58>0,H58<F58+G58),"Partial",IF(AND(H58=0,TODAY()>C58),"Overdue","Pending"))))
A59: =IF(57<=Tenure,57,"") | B59: =IF(57<=Tenure,C58,"") | C59: =IF(57<=Tenure,WORKDAY.INTL(EDATE(FirstPayDate,56)-1,1,1,ArmenianHolidays),"") | D59: =IF(57<=Tenure,IF(57=Tenure,C59-C58+1,C59-C58),"") | E59: =IF(57<=Tenure,O58,"") | F59: =IF(57<=Tenure,E59*D59*(AnnualRate/100),"") | G59: =IF(57<=Tenure,IF(57=Tenure,E59,EMI-F59),"") | H59: =IF(57<=Tenure,IFERROR(SUMIFS(Payments!$C:$C,Payments!$B:$B,A59),0),"") | I59: =IF(57<=Tenure,IFERROR(AGGREGATE(15,6,Payments!$A$3:$A$200/(Payments!$B$3:$B$200=A59),1),""),"") | J59: =IF(57<=Tenure,IF(H59=0,0,IF(AND(I59<>"",I59<>0,I59<C59),MIN(F59,MAX(0,H59-K59)-IFERROR(MIN(MAX(0,(MAX(0,H59-K59)-F59)/(1-MAX(0,C59-I59)*(AnnualRate/100))),E59,MAX(0,H59-K59)),0)),MIN(F59,MAX(0,H59-K59)))),"") | K59: =IF(57<=Tenure,IF(H59=0,0,MIN(E59,MAX(0,MAX(0,H59-K59)-L59))),"") | L59: =IF(57<=Tenure,MAX(0,F59+G59+J59-K59-L59-M59),"") | M59: =IF(57<=Tenure,IF(57=Tenure,0,MAX(0,E59-M59)),"") | N59: =IF(57>Tenure,"",IF(AND(H59>0,H59>=F59+G59+J59),"Paid",IF(AND(H59>0,H59<F59+G59),"Partial",IF(AND(H59=0,TODAY()>C59),"Overdue","Pending"))))
A60: =IF(58<=Tenure,58,"") | B60: =IF(58<=Tenure,C59,"") | C60: =IF(58<=Tenure,WORKDAY.INTL(EDATE(FirstPayDate,57)-1,1,1,ArmenianHolidays),"") | D60: =IF(58<=Tenure,IF(58=Tenure,C60-C59+1,C60-C59),"") | E60: =IF(58<=Tenure,O59,"") | F60: =IF(58<=Tenure,E60*D60*(AnnualRate/100),"") | G60: =IF(58<=Tenure,IF(58=Tenure,E60,EMI-F60),"") | H60: =IF(58<=Tenure,IFERROR(SUMIFS(Payments!$C:$C,Payments!$B:$B,A60),0),"") | I60: =IF(58<=Tenure,IFERROR(AGGREGATE(15,6,Payments!$A$3:$A$200/(Payments!$B$3:$B$200=A60),1),""),"") | J60: =IF(58<=Tenure,IF(H60=0,0,IF(AND(I60<>"",I60<>0,I60<C60),MIN(F60,MAX(0,H60-K60)-IFERROR(MIN(MAX(0,(MAX(0,H60-K60)-F60)/(1-MAX(0,C60-I60)*(AnnualRate/100))),E60,MAX(0,H60-K60)),0)),MIN(F60,MAX(0,H60-K60)))),"") | K60: =IF(58<=Tenure,IF(H60=0,0,MIN(E60,MAX(0,MAX(0,H60-K60)-L60))),"") | L60: =IF(58<=Tenure,MAX(0,F60+G60+J60-K60-L60-M60),"") | M60: =IF(58<=Tenure,IF(58=Tenure,0,MAX(0,E60-M60)),"") | N60: =IF(58>Tenure,"",IF(AND(H60>0,H60>=F60+G60+J60),"Paid",IF(AND(H60>0,H60<F60+G60),"Partial",IF(AND(H60=0,TODAY()>C60),"Overdue","Pending"))))
A61: =IF(59<=Tenure,59,"") | B61: =IF(59<=Tenure,C60,"") | C61: =IF(59<=Tenure,WORKDAY.INTL(EDATE(FirstPayDate,58)-1,1,1,ArmenianHolidays),"") | D61: =IF(59<=Tenure,IF(59=Tenure,C61-C60+1,C61-C60),"") | E61: =IF(59<=Tenure,O60,"") | F61: =IF(59<=Tenure,E61*D61*(AnnualRate/100),"") | G61: =IF(59<=Tenure,IF(59=Tenure,E61,EMI-F61),"") | H61: =IF(59<=Tenure,IFERROR(SUMIFS(Payments!$C:$C,Payments!$B:$B,A61),0),"") | I61: =IF(59<=Tenure,IFERROR(AGGREGATE(15,6,Payments!$A$3:$A$200/(Payments!$B$3:$B$200=A61),1),""),"") | J61: =IF(59<=Tenure,IF(H61=0,0,IF(AND(I61<>"",I61<>0,I61<C61),MIN(F61,MAX(0,H61-K61)-IFERROR(MIN(MAX(0,(MAX(0,H61-K61)-F61)/(1-MAX(0,C61-I61)*(AnnualRate/100))),E61,MAX(0,H61-K61)),0)),MIN(F61,MAX(0,H61-K61)))),"") | K61: =IF(59<=Tenure,IF(H61=0,0,MIN(E61,MAX(0,MAX(0,H61-K61)-L61))),"") | L61: =IF(59<=Tenure,MAX(0,F61+G61+J61-K61-L61-M61),"") | M61: =IF(59<=Tenure,IF(59=Tenure,0,MAX(0,E61-M61)),"") | N61: =IF(59>Tenure,"",IF(AND(H61>0,H61>=F61+G61+J61),"Paid",IF(AND(H61>0,H61<F61+G61),"Partial",IF(AND(H61=0,TODAY()>C61),"Overdue","Pending"))))
A62: =IF(60<=Tenure,60,"") | B62: =IF(60<=Tenure,C61,"") | C62: =IF(60<=Tenure,WORKDAY.INTL(EDATE(FirstPayDate,59)-1,1,1,ArmenianHolidays),"") | D62: =IF(60<=Tenure,IF(60=Tenure,C62-C61+1,C62-C61),"") | E62: =IF(60<=Tenure,O61,"") | F62: =IF(60<=Tenure,E62*D62*(AnnualRate/100),"") | G62: =IF(60<=Tenure,IF(60=Tenure,E62,EMI-F62),"") | H62: =IF(60<=Tenure,IFERROR(SUMIFS(Payments!$C:$C,Payments!$B:$B,A62),0),"") | I62: =IF(60<=Tenure,IFERROR(AGGREGATE(15,6,Payments!$A$3:$A$200/(Payments!$B$3:$B$200=A62),1),""),"") | J62: =IF(60<=Tenure,IF(H62=0,0,IF(AND(I62<>"",I62<>0,I62<C62),MIN(F62,MAX(0,H62-K62)-IFERROR(MIN(MAX(0,(MAX(0,H62-K62)-F62)/(1-MAX(0,C62-I62)*(AnnualRate/100))),E62,MAX(0,H62-K62)),0)),MIN(F62,MAX(0,H62-K62)))),"") | K62: =IF(60<=Tenure,IF(H62=0,0,MIN(E62,MAX(0,MAX(0,H62-K62)-L62))),"") | L62: =IF(60<=Tenure,MAX(0,F62+G62+J62-K62-L62-M62),"") | M62: =IF(60<=Tenure,IF(60=Tenure,0,MAX(0,E62-M62)),"") | N62: =IF(60>Tenure,"",IF(AND(H62>0,H62>=F62+G62+J62),"Paid",IF(AND(H62>0,H62<F62+G62),"Partial",IF(AND(H62=0,TODAY()>C62),"Overdue","Pending"))))

Sheet Payments
A1: PAYMENT ENTRY TABLE
A2: Payment Date | B2: Installment # | C2: Amount | D2: Notes | E2: Allocation Check
A3: 45703 | C3: =EMI | D3: On-time month 1 | E3: =IFERROR("Pen: "&TEXT(VLOOKUP(B3,Schedule!$A:$P,11,0),"#,##0.000")&" | Int: "&TEXT(VLOOKUP(B3,Schedule!$A:$P,12,0),"#,##0.000")&" | Prin: "&TEXT(VLOOKUP(B3,Schedule!$A:$P,13,0),"#,##0.000"),"")
A4: 45736 | C4: =EMI/2 | D4: Partial — 50% — 5 days late | E4: =IFERROR("Pen: "&TEXT(VLOOKUP(B4,Schedule!$A:$P,11,0),"#,##0.000")&" | Int: "&TEXT(VLOOKUP(B4,Schedule!$A:$P,12,0),"#,##0.000")&" | Prin: "&TEXT(VLOOKUP(B4,Schedule!$A:$P,13,0),"#,##0.000"),"")
A5: 45762 | C5: =EMI*2 | D5: Double payment — extra principal | E5: =IFERROR("Pen: "&TEXT(VLOOKUP(B5,Schedule!$A:$P,11,0),"#,##0.000")&" | Int: "&TEXT(VLOOKUP(B5,Schedule!$A:$P,12,0),"#,##0.000")&" | Prin: "&TEXT(VLOOKUP(B5,Schedule!$A:$P,13,0),"#,##0.000"),"")

Sheet Reconciliation
A1: RECONCILIATION DASHBOARD
A3: PRINCIPAL RECONCILIATION
A4: Metric | B4: Expected / Target | C4: =SUM(Schedule!$G$3:$G$62) | D4: Difference / Check
A5: Original Loan Amount | B5: =LoanAmount | C5: =SUM(Schedule!$M$3:$M$62) | D5: =B4-C4
A6: Total Principal Paid | B6: =LoanAmount-SUM(Schedule!$M$3:$M$62) | C6: =IFERROR(SUMIF(Schedule!$P$3:$P$62,"<>Paid",Schedule!$G$3:$G$62),0) | D6: =B5-C5
A7: Outstanding Principal | B7: =LoanAmount-SUM(Schedule!$M$3:$M$62) | C7: =IFERROR(INDEX(Schedule!$O$3:$O$62,MATCH(TRUE,Schedule!$O$3:$O$62<>"",0)+COUNTIF(Schedule!$A$3:$A$62,"<="&Tenure)-1),0) | D7: =IF(ABS(B6-C6)<1,"OK ✓","DISCREPANCY ✗")
A9: INTEREST RECONCILIATION
A10: Metric | B10: Expected / Target | C10: =SUM(Schedule!$F$3:$F$62) | D10: Difference / Check
A11: Total Interest Expected | B11: =Inputs!B19 | C11: =SUM(Schedule!$L$3:$L$62) | D11: =B10-C10
A12: Total Interest Paid | B12: =SUM(Schedule!$F$3:$F$62)-SUM(Schedule!$L$3:$L$62) | C12: =SUMIF(Schedule!$P$3:$P$62,"<>Paid",Schedule!$F$3:$F$62) | D12: =B11-C11
A13: Outstanding Interest | B13: =SUM(Schedule!$F$3:$F$62)-SUM(Schedule!$L$3:$L$62) | C13: =SUMIF(Schedule!$P$3:$P$62,"<>Paid",Schedule!$F$3:$F$62) | D13: =IF(ABS(B12-C12)<1,"OK ✓","DISCREPANCY ✗")
A16: Metric | B16: =SUM(Schedule!$J$3:$J$62) | C16: =SUM(Schedule!$J$3:$J$62) | D16: Difference / Check
A17: Total Penalties Assessed | B17: =SUM(Schedule!$K$3:$K$62) | C17: =SUM(Schedule!$K$3:$K$62) | D17: =B16-C16
A18: Total Penalties Paid | B18: =SUM(Schedule!$K$3:$K$62) | C18: =SUM(Schedule!$K$3:$K$62) | D18: =B17-C17
A19: Outstanding Penalties | B19: =B16-B17 | C19: =C16-C17 | D19: =IF(ABS(B18-C18)<0.001,"OK ✓","DISCREPANCY ✗")
A21: OVERALL SUMMARY
A22: Metric | B22: Expected / Target | C22: Actual (from schedule) | D22: Difference / Check
A23: Total EMI Scheduled | B23: =SUM(Payments!$C$3:$C$200) | C23: =SUM(Schedule!$H$3:$H$62) | D23: =B22-C22
A24: Total Cash Received | B24: =MAX(Schedule!$O$3:$O$62) | C24: =LoanAmount-SUM(Schedule!$M$3:$M$62) | D24: =IF(ABS(B23-C23)<0.001,"OK ✓","MATCH ✓")
A25: Current Outstanding Balance | B25: =MAX(Schedule!$O$3:$O$62) | C25: =LoanAmount-SUM(Schedule!$M$3:$M$62) | D25: =IF(ABS(B24-C24)<1,"BALANCED ✓","DISCREPANCY ✗")
A26: Overdue Installments | B26: =COUNTIF(Schedule!$P$3:$P$62,"Overdue") | C26: =COUNTIF(Schedule!$P$3:$P$62,"Partial") | D26: Overdue | Partial
