Workbook
Name ArmenianHolidays: Holidays!$A$2:$A$92
Name LoanAmount: Inputs!$B$4
Name AnnualRate: Inputs!$B$5
Name FeeRate: Inputs!$B$6
Name StartDate: Inputs!$B$8
Name FirstPayDate: Inputs!$B$9
Name Tenure: Inputs!$B$10
Name DayConvention: Inputs!$B$12
Name ExtraPayMode: Inputs!$B$13
Name MonthlyRate: Inputs!$B$16
Name EMI: Inputs!$B$17

Sheet Holidays
A1: Armenian Public Holidays
A2: 45292
A3: 45293
A4: 45297
A5: 45318
A6: 45319
A7: 45359
A8: 45406
A9: 45413
A10: 45421
A11: 45440
A12: 45478
A13: 45556
... A92: 47848

Sheet Inputs
A1: DC LOAN CALCULATOR — Amortized Schedule
A2: Parameter | B2: Value | C2: Units / Notes
A3: LOAN PARAMETERS
A4: Loan Amount | B4: 1500000 | C4: AMD
A5: Annual Interest Rate | B5: 0.11 | C5: Daily % stored in DB (0.11 = 0.11%/day = 40.15%/yr) — e.g. contract 28 = 0.11
A6: Annual Fee Rate | B6: 0 | C6: Decimal (0.02 = 2%)
A8: Loan Start Date | B8: 46091 | C8: YYYY-MM-DD
A9: First Payment Date | B9: 46122 | C9: YYYY-MM-DD
A10: Tenure (months) | B10: 60 | C10: months
A11: CONFIGURATION
A12: Day Count Convention | B12: Actual | C12: dropdown
A13: Extra Payment Mode | B13: Reduce Tenure | C13: dropdown
A15: DERIVED CALCULATIONS (formulas — do not edit)
A16: Combined Monthly Rate | B16: =B5*365/100/12+B6/100/12 | C16: Source: ContractService.php L466-467 — interestAnnualPercent = rate*365 → monthlyRate = annualPercent/100/12 (rate stored as daily-%, so *365 gives annual-%, /100 gives decimal, /12 gives monthly)
A17: Monthly Payment (EMI) | B17: =-PMT(B16,B10,B4) | C17: Source: ContractService.php L474 — -excelPmt(allMonthlyRate, months, loanAmount)
A18: Total Scheduled Payments | B18: =B17*B10 | C18: Sum of all EMIs
A19: Total Interest + Fee Cost | B19: =B18-B4 | C19: Total cost of credit
A20: Effective Annual Rate (approx) | B20: =(1+B16)^12-1 | C20: Approximate — backend uses XIRR; see EffectiveRateService.php

Sheet Schedule
A1: AMORTIZATION SCHEDULE — DC_New_backend logic
A2: # | B2: Period Start | C2: Due Date (adj.) | D2: Days | E2: Opening Balance | F2: Accrued Interest | G2: Principal Due | H2: Payment Received | I2: Payment Date | J2: Interest Paid | K2: Principal Paid | L2: Unpaid Carried | M2: Closing Balance | N2: Status
A3: 1 | B3: 46091 | C3: 46122 | D3: 31 | E3: 1500000 | F3: 51150 | G3: 7126.9397 | H3: 58276.94 | I3: 45703 | J3: 51150 | K3: 7126.9397 | L3: 0 | M3: 1492873.1 | N3: Paid
A4: 2 | B4: 46122 | C4: 46153 | D4: 31 | E4: 1492873.1 | F4: 50906.971 | G4: 7369.9684 | H4: 87415.41 | I4: 45736 | J4: 29138.47 | K4: 0 | L4: 29138.47 | M4: 1492873.1 | N4: Partial
A5: 3 | B5: 46153 | C5: 46183 | D5: 30 | E5: 1485503.1 | F5: 49021.602 | G5: 9255.3377 | H5: 58276.94 | I5: 45762 | J5: 49021.602 | K5: 9255.3377 | L5: 0 | M5: 1476247.8 | N5: Partial
A6: 4 | B6: 46183 | C6: 46213 | D6: 30 | E6: 1476247.8 | F6: 48716.176 | G6: 0 | H6: 0 | J6: 0 | K6: 0 | L6: 48716.176 | M6: 1476247.8 | N6: Pending
A7: 5 | B7: 46213 | C7: 46244 | D7: 31 | E7: 1476247.8 | F7: 50340.048 | G7: 0 | H7: 0 | J7: 0 | K7: 0 | L7: 50340.048 | M7: 1476247.8 | N7: Pending
A8: 6 | B8: 46244 | C8: 46275 | D8: 31 | E8: 1476247.8 | F8: 50340.048 | G8: 0 | H8: 0 | J8: 0 | K8: 0 | L8: 50340.048 | M8: 1476247.8 | N8: Pending
A9: 7 | B9: 46275 | C9: 46307 | D9: 32 | E9: 1476247.8 | F9: 51963.921 | G9: 0 | H9: 0 | J9: 0 | K9: 0 | L9: 51963.921 | M9: 1476247.8 | N9: Pending
A10: 8 | B10: 46307 | C10: 46336 | D10: 29 | E10: 1476247.8 | F10: 47092.303 | G10: 0 | H10: 0 | J10: 0 | K10: 0 | L10: 47092.303 | M10: 1476247.8 | N10: Pending
A11: 9 | B11: 46336 | C11: 46366 | D11: 30 | E11: 1476247.8 | F11: 48716.176 | G11: 0 | H11: 0 | J11: 0 | K11: 0 | L11: 48716.176 | M11: 1476247.8 | N11: Pending
A12: 10 | B12: 46366 | C12: 46398 | D12: 32 | E12: 1476247.8 | F12: 51963.921 | G12: 6981.0649 | H12: 0 | J12: 0 | K12: 0 | L12: 58944.986 | M12: 1476247.8 | N12: Pending
A13: 11 | B13: 46398 | C13: 46428 | D13: 30 | E13: 1469266.7 | F13: 48485.801 | G13: 11714.278 | H13: 0 | J13: 0 | K13: 0 | L13: 60200.079 | M13: 1469266.7 | N13: Pending
A14: 12 | B14: 46428 | C14: 46456 | D14: 28 | E14: 1457552.4 | F14: 44892.614 | G14: 15179.255 | H14: 0 | J14: 0 | K14: 0 | L14: 60071.869 | M14: 1457552.4 | N14: Pending
A15: 13 | B15: 46456 | C15: 46489 | D15: 33 | E15: 1442373.2 | F15: 52358.146 | G15: 8034.2471 | H15: 0 | J15: 0 | K15: 0 | L15: 60392.393 | M15: 1442373.2 | N15: Pending
A16: 14 | B16: 46489 | C16: 46517 | D16: 28 | E16: 1434338.9 | F16: 44177.638 | G16: 15894.231 | H16: 0 | J16: 0 | K16: 0 | L16: 60071.869 | M16: 1434338.9 | N16: Pending
A17: 15 | B17: 46517 | C17: 46548 | D17: 31 | E17: 1418444.7 | F17: 48368.964 | G17: 11895.22 | H17: 0 | J17: 0 | K17: 0 | L17: 60264.183 | M17: 1418444.7 | N17: Pending
... A62: 60 | B62: 47889 | C62: 47917 | D62: 28 | E62: 134705.25 | F62: 4148.9216 | G62: 76428.306 | H62: 0 | J62: 0 | K62: 0 | L62: 80577.228 | M62: 134705.25 | N62: Pending

Sheet Payments
A1: PAYMENT ENTRY TABLE
A2: Payment Date | B2: Installment # | C2: Amount | D2: Notes | E2: Allocation Check
A3: 45703 | B3: 1 | C3: =EMI | D3: On-time month 1 | E3: =IFERROR("Pen: "&TEXT(VLOOKUP(B3,Schedule!$A:$P,11,0),"#,##0.000")&" | Int: "&TEXT(VLOOKUP(B3,Schedule!$A:$P,12,0),"#,##0.000")&" | Prin: "&TEXT(VLOOKUP(B3,Schedule!$A:$P,13,0),"#,##0.000"),"")
A4: 45736 | B4: 2 | C4: =EMI/2 | D4: Partial — 50% — 5 days late | E4: =IFERROR("Pen: "&TEXT(VLOOKUP(B4,Schedule!$A:$P,11,0),"#,##0.000")&" | Int: "&TEXT(VLOOKUP(B4,Schedule!$A:$P,12,0),"#,##0.000")&" | Prin: "&TEXT(VLOOKUP(B4,Schedule!$A:$P,13,0),"#,##0.000"),"")
A5: 45762 | B5: 3 | C5: =EMI*2 | D5: Double payment — extra principal | E5: =IFERROR("Pen: "&TEXT(VLOOKUP(B5,Schedule!$A:$P,11,0),"#,##0.000")&" | Int: "&TEXT(VLOOKUP(B5,Schedule!$A:$P,12,0),"#,##0.000")&" | Prin: "&TEXT(VLOOKUP(B5,Schedule!$A:$P,13,0),"#,##0.000"),"")

Sheet Reconciliation
A1: RECONCILIATION DASHBOARD
A3: PRINCIPAL RECONCILIATION
A4: Metric | B4: Expected / Target | C4: =SUM(Schedule!$G$3:$G$62) | D4: Difference / Check
A5: Original Loan Amount | B5: =LoanAmount | C5: =SUM(Schedule!$M$3:$M$62) | D5: =B4-C4
A6: Total Principal Paid | B6: =LoanAmount-SUM(Schedule!$M$3:$M$62) | C6: =IFERROR(SUMIF(Schedule!$P$3:$P$62,"<>Paid",Schedule!$G$3:$G$62),0) | D6: =B5-C5
A7: Outstanding Principal | B7: =LoanAmount-SUM(Schedule!$M$3:$M$62) | C7: =IFERROR(INDEX(Schedule!$O$3:$O$62,MATCH(TRUE,Schedule!$O$3:$O$62<>"",0)+COUNTIF(Schedule!$A$3:$A$62,"<="&Tenure)-1),0) | D7: =IF(ABS(B6-C6)<1,"OK ✓","DISCREPANCY ✗")
A9: INTEREST RECONCILIATION
A10: Metric | B10: Expected / Target | C10: =SUM(Schedule!$F$3:$F$62) | D10: Difference / Check
A11: Total Interest Expected | B11: =Inputs!B19 | C11: =SUM(Schedule!$L$3:$L$62) | D11: =B10-C10
A12: Total Interest Paid | B12: =SUM(Schedule!$F$3:$F$62)-SUM(Schedule!$L$3:$L$62) | C12: =SUMIF(Schedule!$P$3:$P$62,"<>Paid",Schedule!$F$3:$F$62) | D12: =B11-C11
A13: Outstanding Interest | B13: =SUM(Schedule!$F$3:$F$62)-SUM(Schedule!$L$3:$L$62) | C13: =SUMIF(Schedule!$P$3:$P$62,"<>Paid",Schedule!$F$3:$F$62) | D13: =IF(ABS(B12-C12)<1,"OK ✓","DISCREPANCY ✗")
A16: Metric | B16: =SUM(Schedule!$J$3:$J$62) | C16: =SUM(Schedule!$J$3:$J$62) | D16: Difference / Check
A17: Total Penalties Assessed | B17: =SUM(Schedule!$K$3:$K$62) | C17: =SUM(Schedule!$K$3:$K$62) | D17: =B16-C16
A18: Total Penalties Paid | B18: =SUM(Schedule!$K$3:$K$62) | C18: =SUM(Schedule!$K$3:$K$62) | D18: =B17-C17
A19: Outstanding Penalties | B19: =B16-B17 | C19: =C16-C17 | D19: =IF(ABS(B18-C18)<0.001,"OK ✓","DISCREPANCY ✗")
A21: OVERALL SUMMARY
A22: Metric | B22: Expected / Target | C22: Actual (from schedule) | D22: Difference / Check
A23: Total EMI Scheduled | B23: =SUM(Payments!$C$3:$C$200) | C23: =SUM(Schedule!$H$3:$H$62) | D23: =B22-C22
A24: Total Cash Received | B24: =MAX(Schedule!$O$3:$O$62) | C24: =LoanAmount-SUM(Schedule!$M$3:$M$62) | D24: =IF(ABS(B23-C23)<0.001,"OK ✓","MATCH ✓")
A25: Current Outstanding Balance | B25: =MAX(Schedule!$O$3:$O$62) | C25: =LoanAmount-SUM(Schedule!$M$3:$M$62) | D25: =IF(ABS(B24-C24)<1,"BALANCED ✓","DISCREPANCY ✗")
A26: Overdue Installments | B26: =COUNTIF(Schedule!$P$3:$P$62,"Overdue") | C26: =COUNTIF(Schedule!$P$3:$P$62,"Partial") | D26: Overdue | Partial

Sheet Backend_Recalc
A1: Installment | B1: From Date | C1: Due Date | D1: Days | E1: Opening | F1: Interest Due | G1: Principal Due | H1: Penalty Due | I1: Paid Interest | J1: Paid Principal | K1: Paid Penalty | L1: Paid Total | M1: Closing | N1: Status | O1: Last Payment Date
A2: 1 | B2: 46091 | C2: 46122 | D2: 31 | E2: 1500000 | F2: 51150 | G2: 7126.9397 | H2: 0 | I2: 51150 | J2: 7126.9397 | K2: 0 | L2: 58276.94 | M2: 1492873.1 | N2: Paid | O2: 45703
A3: 2 | B3: 46122 | C3: 46153 | D3: 31 | E3: 1492873.1 | F3: 50906.971 | G3: 7369.9684 | H3: 0 | I3: 29138.47 | J3: 0 | K3: 0 | L3: 87415.41 | M3: 1492873.1 | N3: Partial | O3: 45736
A4: 3 | B4: 46153 | C4: 46183 | D4: 30 | E4: 1485503.1 | F4: 49021.602 | G4: 9255.3377 | H4: 0 | I4: 49021.602 | J4: 9255.3377 | K4: 0 | L4: 58276.94 | M4: 1476247.8 | N4: Partial | O4: 45762
A5: 4 | B5: 46183 | C5: 46213 | D5: 30 | E5: 1476247.8 | F5: 48716.176 | G5: 0 | H5: 0 | I5: 0 | J5: 0 | K5: 0 | L5: 0 | M5: 1476247.8 | N5: Pending
A6: 5 | B6: 46213 | C6: 46244 | D6: 31 | E6: 1476247.8 | F6: 50340.048 | G6: 0 | H6: 0 | I6: 0 | J6: 0 | K6: 0 | L6: 0 | M6: 1476247.8 | N6: Pending
A7: 6 | B7: 46244 | C7: 46275 | D7: 31 | E7: 1476247.8 | F7: 50340.048 | G7: 0 | H7: 0 | I7: 0 | J7: 0 | K7: 0 | L7: 0 | M7: 1476247.8 | N7: Pending
A8: 7 | B8: 46275 | C8: 46307 | D8: 32 | E8: 1476247.8 | F8: 51963.921 | G8: 0 | H8: 0 | I8: 0 | J8: 0 | K8: 0 | L8: 0 | M8: 1476247.8 | N8: Pending
A9: 8 | B9: 46307 | C9: 46336 | D9: 29 | E9: 1476247.8 | F9: 47092.303 | G9: 0 | H9: 0 | I9: 0 | J9: 0 | K9: 0 | L9: 0 | M9: 1476247.8 | N9: Pending
A10: 9 | B10: 46336 | C10: 46366 | D10: 30 | E10: 1476247.8 | F10: 48716.176 | G10: 0 | H10: 0 | I10: 0 | J10: 0 | K10: 0 | L10: 0 | M10: 1476247.8 | N10: Pending
A11: 10 | B11: 46366 | C11: 46398 | D11: 32 | E11: 1476247.8 | F11: 51963.921 | G11: 6981.0649 | H11: 0 | I11: 0 | J11: 0 | K11: 0 | L11: 0 | M11: 1476247.8 | N11: Pending
A12: 11 | B12: 46398 | C12: 46428 | D12: 30 | E12: 1469266.7 | F12: 48485.801 | G12: 11714.278 | H12: 0 | I12: 0 | J12: 0 | K12: 0 | L12: 0 | M12: 1469266.7 | N12: Pending
A13: 12 | B13: 46428 | C13: 46456 | D13: 28 | E13: 1457552.4 | F13: 44892.614 | G13: 15179.255 | H13: 0 | I13: 0 | J13: 0 | K13: 0 | L13: 0 | M13: 1457552.4 | N13: Pending
A14: 13 | B14: 46456 | C14: 46489 | D14: 33 | E14: 1442373.2 | F14: 52358.146 | G14: 8034.2471 | H14: 0 | I14: 0 | J14: 0 | K14: 0 | L14: 0 | M14: 1442373.2 | N14: Pending
A15: 14 | B15: 46489 | C15: 46517 | D15: 28 | E15: 1434338.9 | F15: 44177.638 | G15: 15894.231 | H15: 0 | I15: 0 | J15: 0 | K15: 0 | L15: 0 | M15: 1434338.9 | N15: Pending
A16: 15 | B16: 46517 | C16: 46548 | D16: 31 | E16: 1418444.7 | F16: 48368.964 | G16: 11895.22 | H16: 0 | I16: 0 | J16: 0 | K16: 0 | L16: 0 | M16: 1418444.7 | N16: Pending
... A61: 60 | B61: 47889 | C61: 47917 | D61: 28 | E61: 134705.25 | F61: 4148.9216 | G61: 76428.306 | H61: 0 | I61: 0 | J61: 0 | K61: 0 | L61: 0 | M61: 134705.25 | N61: Pending
